{
  "id": 128574,
  "dim_x": 2,
  "dim_y": 2,
  "is_transparent": true,
  "unknown_19": 1,
  "unknown_27": false,
  "morphs_1": {
    "varbit": 54707,
    "ids": [
      null,
      null,
      null,
      null,
      null,
      null,
      null,
      null,
      null,
      null,
      null,
      null,
      null,
      null,
      null,
      null,
      null,
      null,
      null,
      null,
      null,
      null,
      null,
      null,
      null,
      null,
      null,
      null,
      null,
      null,
      null,
      null,
      null,
      null,
      null,
      null,
      null,
      null,
      null,
      null,
      null,
      null,
      null,
      null,
      null,
      null,
      null,
      null,
      null,
      null,
      128575
    ]
  }
}