{
  "id": 16331,
  "dim_x": 2,
  "dim_y": 2,
  "unknown_19": 1,
  "unknown_27": false,
  "morphs_1": {
    "varbit": 12510,
    "ids": [
      16332,
      16333,
      16334,
      16335,
      16336,
      16337,
      16338,
      16339,
      16340,
      16341,
      16332,
      16333,
      16334,
      16335,
      16336,
      16337,
      16338,
      16339,
      16340,
      16341,
      16332,
      16333,
      16334,
      16335,
      16336,
      16337,
      16338,
      16339,
      16340,
      16341,
      16332,
      16333,
      16334,
      16335,
      16336,
      16337,
      16338,
      16339,
      16340,
      16341,
      16332,
      16333,
      16334,
      16335,
      16336,
      16337,
      16338,
      16339,
      16340,
      16341,
      16332
    ]
  }
}