{
  "id": 30844,
  "models": {
    "0": [
      27345
    ],
    "1": [
      27320
    ],
    "2": [
      27344
    ],
    "3": [
      27332
    ],
    "9": [
      27338
    ]
  },
  "unknown_19": 0,
  "unknown_22": true,
  "unknown_27": false,
  "unknown_28": 16,
  "ambient": 25,
  "contrast": 15,
  "colours": [
    [
      10281,
      10266
    ],
    [
      10285,
      10275
    ],
    [
      10289,
      10283
    ],
    [
      6315,
      5908
    ],
    [
      6323,
      5665
    ],
    [
      8410,
      8427
    ]
  ]
}