{
  "id": 47213,
  "unknown_19": 1,
  "unknown_21": true,
  "ambient": 25,
  "contrast": 15,
  "morphs_1": {
    "varbit": 11105,
    "ids": [
      null,
      null,
      null,
      null,
      null,
      null,
      null,
      null,
      null,
      null,
      null,
      null,
      null,
      null,
      null,
      null,
      null,
      null,
      null,
      null,
      null,
      null,
      null,
      null,
      null,
      null,
      null,
      null,
      null,
      null,
      null,
      null,
      null,
      null,
      null,
      null,
      null,
      null,
      null,
      null,
      null,
      null,
      null,
      null,
      null,
      null,
      null,
      null,
      null,
      null,
      47214,
      null,
      null,
      null,
      null,
      null,
      null,
      null,
      null,
      null,
      47214,
      null,
      null,
      null,
      null,
      47214,
      47214,
      47214,
      null,
      null,
      47214,
      null,
      null,
      47214,
      null,
      47214,
      null,
      null,
      null,
      null,
      47215,
      null,
      null,
      null,
      null,
      null,
      null,
      null,
      null,
      null,
      47215
    ]
  }
}