{
  "id": 59833,
  "models": {
    "10": [
      14640
    ]
  },
  "is_transparent": true,
  "unknown_19": 0,
  "unknown_27": false,
  "ambient": 25,
  "contrast": 15,
  "colours": [
    [
      5318,
      7356
    ],
    [
      5310,
      7350
    ],
    [
      5294,
      7342
    ],
    [
      5286,
      7334
    ],
    [
      5278,
      7326
    ],
    [
      5270,
      7318
    ],
    [
      5262,
      7310
    ]
  ],
  "textures": {
    "1989": 2023
  },
  "unknown_44": 254,
  "occludes_2": false
}