{
  "id": 61549,
  "models": {
    "10": [
      57487
    ]
  },
  "name": "Rocks",
  "dim_x": 2,
  "dim_y": 2,
  "unknown_19": 1,
  "unknown_21": true,
  "unknown_27": false,
  "ambient": 20,
  "contrast": 25,
  "colours": [
    [
      6670,
      34881
    ],
    [
      6674,
      34887
    ],
    [
      6550,
      34895
    ],
    [
      6552,
      34903
    ],
    [
      6554,
      34909
    ],
    [
      6556,
      34909
    ],
    [
      32874,
      43125
    ]
  ],
  "occludes_2": false
}