{
  "id": 65441,
  "models": {
    "10": [
      25024
    ]
  },
  "name": "Bones",
  "dim_x": 2,
  "dim_y": 4,
  "unknown_21": true,
  "colours": [
    [
      11435,
      8368
    ],
    [
      11439,
      8372
    ],
    [
      11431,
      8364
    ],
    [
      11433,
      8366
    ],
    [
      11427,
      8360
    ],
    [
      11437,
      8370
    ],
    [
      13590,
      8342
    ],
    [
      11443,
      8376
    ],
    [
      11423,
      8356
    ],
    [
      11415,
      8336
    ],
    [
      11546,
      8479
    ],
    [
      11429,
      8362
    ],
    [
      13759,
      13375
    ]
  ],
  "occludes_2": false
}