{
  "id": 73936,
  "models": {
    "10": [
      72332
    ]
  },
  "dim_x": 4,
  "dim_y": 5,
  "unknown_17": false,
  "unknown_19": 0,
  "ambient": 20,
  "contrast": 25,
  "colours": [
    [
      597,
      6737
    ],
    [
      202,
      6342
    ],
    [
      209,
      6349
    ],
    [
      601,
      6741
    ],
    [
      21187,
      42698
    ],
    [
      17850,
      39361
    ],
    [
      17857,
      39368
    ],
    [
      22217,
      43728
    ]
  ],
  "textures": {
    "1584": 1551
  },
  "mirror": true,
  "model": false,
  "unknown_88": false,
  "occludes_2": false
}