[
  {
    "plane": 2,
    "i": 19,
    "j": 3,
    "x": 19,
    "y": 20,
    "id": 115194,
    "type": 10,
    "rotation": 3
  },
  {
    "plane": 2,
    "i": 19,
    "j": 3,
    "x": 44,
    "y": 26,
    "id": 115194,
    "type": 11,
    "rotation": 2
  },
  {
    "plane": 0,
    "i": 52,
    "j": 53,
    "x": 52,
    "y": 20,
    "id": 115194,
    "type": 10,
    "rotation": 0
  },
  {
    "plane": 1,
    "i": 60,
    "j": 154,
    "x": 33,
    "y": 12,
    "id": 115194,
    "type": 10,
    "rotation": 2
  },
  {
    "plane": 1,
    "i": 60,
    "j": 154,
    "x": 56,
    "y": 22,
    "id": 115194,
    "type": 10,
    "rotation": 0
  }
]