[
  {
    "plane": 0,
    "i": 11,
    "j": 4,
    "x": 4,
    "y": 58,
    "id": 119992,
    "type": 11,
    "rotation": 2
  },
  {
    "plane": 0,
    "i": 11,
    "j": 5,
    "x": 26,
    "y": 52,
    "id": 119992,
    "type": 11,
    "rotation": 2
  },
  {
    "plane": 0,
    "i": 11,
    "j": 5,
    "x": 38,
    "y": 59,
    "id": 119992,
    "type": 11,
    "rotation": 3
  },
  {
    "plane": 0,
    "i": 11,
    "j": 5,
    "x": 46,
    "y": 23,
    "id": 119992,
    "type": 11,
    "rotation": 3
  },
  {
    "plane": 0,
    "i": 27,
    "j": 19,
    "x": 4,
    "y": 58,
    "id": 119992,
    "type": 11,
    "rotation": 2
  },
  {
    "plane": 0,
    "i": 27,
    "j": 20,
    "x": 63,
    "y": 3,
    "id": 119992,
    "type": 11,
    "rotation": 0
  },
  {
    "plane": 0,
    "i": 27,
    "j": 20,
    "x": 26,
    "y": 52,
    "id": 119992,
    "type": 11,
    "rotation": 2
  },
  {
    "plane": 0,
    "i": 27,
    "j": 20,
    "x": 38,
    "y": 59,
    "id": 119992,
    "type": 11,
    "rotation": 3
  },
  {
    "plane": 0,
    "i": 27,
    "j": 20,
    "x": 46,
    "y": 23,
    "id": 119992,
    "type": 11,
    "rotation": 3
  },
  {
    "plane": 0,
    "i": 27,
    "j": 29,
    "x": 4,
    "y": 58,
    "id": 119992,
    "type": 11,
    "rotation": 2
  },
  {
    "plane": 0,
    "i": 27,
    "j": 30,
    "x": 63,
    "y": 3,
    "id": 119992,
    "type": 11,
    "rotation": 0
  },
  {
    "plane": 0,
    "i": 27,
    "j": 30,
    "x": 26,
    "y": 52,
    "id": 119992,
    "type": 11,
    "rotation": 2
  },
  {
    "plane": 0,
    "i": 27,
    "j": 30,
    "x": 38,
    "y": 59,
    "id": 119992,
    "type": 11,
    "rotation": 3
  },
  {
    "plane": 0,
    "i": 27,
    "j": 30,
    "x": 46,
    "y": 23,
    "id": 119992,
    "type": 11,
    "rotation": 3
  }
]