[
  {
    "plane": 0,
    "i": 10,
    "j": 4,
    "x": 26,
    "y": 33,
    "id": 120001,
    "type": 22,
    "rotation": 3
  },
  {
    "plane": 0,
    "i": 10,
    "j": 4,
    "x": 39,
    "y": 13,
    "id": 120001,
    "type": 22,
    "rotation": 1
  },
  {
    "plane": 0,
    "i": 10,
    "j": 4,
    "x": 48,
    "y": 6,
    "id": 120001,
    "type": 22,
    "rotation": 0
  },
  {
    "plane": 0,
    "i": 10,
    "j": 4,
    "x": 49,
    "y": 0,
    "id": 120001,
    "type": 22,
    "rotation": 0
  },
  {
    "plane": 0,
    "i": 15,
    "j": 4,
    "x": 16,
    "y": 46,
    "id": 120001,
    "type": 22,
    "rotation": 3
  },
  {
    "plane": 0,
    "i": 15,
    "j": 4,
    "x": 18,
    "y": 48,
    "id": 120001,
    "type": 22,
    "rotation": 3
  },
  {
    "plane": 0,
    "i": 15,
    "j": 4,
    "x": 21,
    "y": 54,
    "id": 120001,
    "type": 22,
    "rotation": 0
  },
  {
    "plane": 0,
    "i": 15,
    "j": 4,
    "x": 25,
    "y": 48,
    "id": 120001,
    "type": 22,
    "rotation": 0
  },
  {
    "plane": 0,
    "i": 15,
    "j": 4,
    "x": 27,
    "y": 57,
    "id": 120001,
    "type": 22,
    "rotation": 0
  },
  {
    "plane": 0,
    "i": 15,
    "j": 4,
    "x": 40,
    "y": 31,
    "id": 120001,
    "type": 22,
    "rotation": 3
  },
  {
    "plane": 0,
    "i": 15,
    "j": 4,
    "x": 46,
    "y": 56,
    "id": 120001,
    "type": 22,
    "rotation": 0
  },
  {
    "plane": 0,
    "i": 15,
    "j": 4,
    "x": 48,
    "y": 58,
    "id": 120001,
    "type": 22,
    "rotation": 3
  },
  {
    "plane": 0,
    "i": 15,
    "j": 4,
    "x": 49,
    "y": 48,
    "id": 120001,
    "type": 22,
    "rotation": 0
  },
  {
    "plane": 0,
    "i": 10,
    "j": 5,
    "x": 9,
    "y": 19,
    "id": 120001,
    "type": 22,
    "rotation": 2
  },
  {
    "plane": 0,
    "i": 10,
    "j": 5,
    "x": 32,
    "y": 62,
    "id": 120001,
    "type": 22,
    "rotation": 0
  },
  {
    "plane": 0,
    "i": 11,
    "j": 5,
    "x": 8,
    "y": 60,
    "id": 120001,
    "type": 22,
    "rotation": 0
  },
  {
    "plane": 0,
    "i": 11,
    "j": 5,
    "x": 25,
    "y": 49,
    "id": 120001,
    "type": 22,
    "rotation": 3
  },
  {
    "plane": 0,
    "i": 11,
    "j": 5,
    "x": 25,
    "y": 60,
    "id": 120001,
    "type": 22,
    "rotation": 0
  },
  {
    "plane": 0,
    "i": 11,
    "j": 5,
    "x": 33,
    "y": 57,
    "id": 120001,
    "type": 22,
    "rotation": 1
  },
  {
    "plane": 0,
    "i": 15,
    "j": 5,
    "x": 16,
    "y": 42,
    "id": 120001,
    "type": 22,
    "rotation": 1
  },
  {
    "plane": 0,
    "i": 15,
    "j": 5,
    "x": 17,
    "y": 19,
    "id": 120001,
    "type": 22,
    "rotation": 0
  },
  {
    "plane": 0,
    "i": 15,
    "j": 5,
    "x": 17,
    "y": 28,
    "id": 120001,
    "type": 22,
    "rotation": 1
  },
  {
    "plane": 0,
    "i": 15,
    "j": 5,
    "x": 25,
    "y": 13,
    "id": 120001,
    "type": 22,
    "rotation": 0
  },
  {
    "plane": 0,
    "i": 15,
    "j": 5,
    "x": 27,
    "y": 14,
    "id": 120001,
    "type": 22,
    "rotation": 0
  },
  {
    "plane": 0,
    "i": 15,
    "j": 5,
    "x": 27,
    "y": 21,
    "id": 120001,
    "type": 22,
    "rotation": 0
  },
  {
    "plane": 0,
    "i": 15,
    "j": 5,
    "x": 28,
    "y": 18,
    "id": 120001,
    "type": 22,
    "rotation": 3
  },
  {
    "plane": 0,
    "i": 15,
    "j": 5,
    "x": 36,
    "y": 6,
    "id": 120001,
    "type": 22,
    "rotation": 0
  },
  {
    "plane": 0,
    "i": 15,
    "j": 5,
    "x": 39,
    "y": 2,
    "id": 120001,
    "type": 22,
    "rotation": 2
  },
  {
    "plane": 0,
    "i": 15,
    "j": 5,
    "x": 47,
    "y": 1,
    "id": 120001,
    "type": 22,
    "rotation": 0
  },
  {
    "plane": 0,
    "i": 15,
    "j": 5,
    "x": 47,
    "y": 15,
    "id": 120001,
    "type": 22,
    "rotation": 1
  },
  {
    "plane": 0,
    "i": 15,
    "j": 5,
    "x": 49,
    "y": 39,
    "id": 120001,
    "type": 22,
    "rotation": 1
  },
  {
    "plane": 0,
    "i": 14,
    "j": 6,
    "x": 45,
    "y": 44,
    "id": 120001,
    "type": 22,
    "rotation": 2
  },
  {
    "plane": 0,
    "i": 15,
    "j": 6,
    "x": 5,
    "y": 4,
    "id": 120001,
    "type": 22,
    "rotation": 1
  },
  {
    "plane": 0,
    "i": 15,
    "j": 6,
    "x": 5,
    "y": 20,
    "id": 120001,
    "type": 22,
    "rotation": 1
  },
  {
    "plane": 0,
    "i": 15,
    "j": 6,
    "x": 5,
    "y": 45,
    "id": 120001,
    "type": 22,
    "rotation": 2
  },
  {
    "plane": 0,
    "i": 15,
    "j": 6,
    "x": 19,
    "y": 40,
    "id": 120001,
    "type": 22,
    "rotation": 0
  },
  {
    "plane": 0,
    "i": 15,
    "j": 6,
    "x": 20,
    "y": 21,
    "id": 120001,
    "type": 22,
    "rotation": 3
  },
  {
    "plane": 0,
    "i": 15,
    "j": 6,
    "x": 28,
    "y": 22,
    "id": 120001,
    "type": 22,
    "rotation": 3
  },
  {
    "plane": 0,
    "i": 15,
    "j": 6,
    "x": 32,
    "y": 6,
    "id": 120001,
    "type": 22,
    "rotation": 0
  },
  {
    "plane": 0,
    "i": 15,
    "j": 6,
    "x": 35,
    "y": 10,
    "id": 120001,
    "type": 22,
    "rotation": 3
  },
  {
    "plane": 0,
    "i": 15,
    "j": 6,
    "x": 37,
    "y": 47,
    "id": 120001,
    "type": 22,
    "rotation": 2
  },
  {
    "plane": 0,
    "i": 15,
    "j": 6,
    "x": 39,
    "y": 22,
    "id": 120001,
    "type": 22,
    "rotation": 1
  },
  {
    "plane": 0,
    "i": 15,
    "j": 6,
    "x": 44,
    "y": 36,
    "id": 120001,
    "type": 22,
    "rotation": 0
  },
  {
    "plane": 0,
    "i": 15,
    "j": 6,
    "x": 57,
    "y": 44,
    "id": 120001,
    "type": 22,
    "rotation": 3
  },
  {
    "plane": 0,
    "i": 15,
    "j": 6,
    "x": 58,
    "y": 60,
    "id": 120001,
    "type": 22,
    "rotation": 2
  },
  {
    "plane": 0,
    "i": 16,
    "j": 6,
    "x": 3,
    "y": 60,
    "id": 120001,
    "type": 22,
    "rotation": 2
  },
  {
    "plane": 0,
    "i": 16,
    "j": 6,
    "x": 7,
    "y": 46,
    "id": 120001,
    "type": 22,
    "rotation": 2
  },
  {
    "plane": 0,
    "i": 2,
    "j": 10,
    "x": 62,
    "y": 42,
    "id": 120001,
    "type": 22,
    "rotation": 3
  },
  {
    "plane": 0,
    "i": 3,
    "j": 10,
    "x": 1,
    "y": 38,
    "id": 120001,
    "type": 22,
    "rotation": 2
  },
  {
    "plane": 0,
    "i": 3,
    "j": 10,
    "x": 2,
    "y": 45,
    "id": 120001,
    "type": 22,
    "rotation": 0
  },
  {
    "plane": 0,
    "i": 3,
    "j": 10,
    "x": 3,
    "y": 34,
    "id": 120001,
    "type": 22,
    "rotation": 1
  },
  {
    "plane": 0,
    "i": 3,
    "j": 10,
    "x": 4,
    "y": 45,
    "id": 120001,
    "type": 22,
    "rotation": 3
  },
  {
    "plane": 0,
    "i": 3,
    "j": 10,
    "x": 5,
    "y": 42,
    "id": 120001,
    "type": 22,
    "rotation": 3
  },
  {
    "plane": 0,
    "i": 3,
    "j": 10,
    "x": 6,
    "y": 39,
    "id": 120001,
    "type": 22,
    "rotation": 1
  },
  {
    "plane": 0,
    "i": 26,
    "j": 19,
    "x": 26,
    "y": 33,
    "id": 120001,
    "type": 22,
    "rotation": 3
  },
  {
    "plane": 0,
    "i": 26,
    "j": 19,
    "x": 39,
    "y": 13,
    "id": 120001,
    "type": 22,
    "rotation": 1
  },
  {
    "plane": 0,
    "i": 26,
    "j": 19,
    "x": 48,
    "y": 6,
    "id": 120001,
    "type": 22,
    "rotation": 0
  },
  {
    "plane": 0,
    "i": 26,
    "j": 19,
    "x": 49,
    "y": 0,
    "id": 120001,
    "type": 22,
    "rotation": 0
  },
  {
    "plane": 0,
    "i": 28,
    "j": 19,
    "x": 14,
    "y": 38,
    "id": 120001,
    "type": 22,
    "rotation": 0
  },
  {
    "plane": 0,
    "i": 28,
    "j": 19,
    "x": 21,
    "y": 26,
    "id": 120001,
    "type": 22,
    "rotation": 0
  },
  {
    "plane": 0,
    "i": 28,
    "j": 19,
    "x": 36,
    "y": 33,
    "id": 120001,
    "type": 22,
    "rotation": 0
  },
  {
    "plane": 0,
    "i": 28,
    "j": 19,
    "x": 36,
    "y": 37,
    "id": 120001,
    "type": 22,
    "rotation": 0
  },
  {
    "plane": 0,
    "i": 29,
    "j": 19,
    "x": 8,
    "y": 33,
    "id": 120001,
    "type": 22,
    "rotation": 0
  },
  {
    "plane": 0,
    "i": 29,
    "j": 19,
    "x": 39,
    "y": 30,
    "id": 120001,
    "type": 22,
    "rotation": 0
  },
  {
    "plane": 0,
    "i": 29,
    "j": 19,
    "x": 53,
    "y": 17,
    "id": 120001,
    "type": 22,
    "rotation": 3
  },
  {
    "plane": 0,
    "i": 29,
    "j": 19,
    "x": 57,
    "y": 16,
    "id": 120001,
    "type": 22,
    "rotation": 0
  },
  {
    "plane": 0,
    "i": 29,
    "j": 19,
    "x": 61,
    "y": 38,
    "id": 120001,
    "type": 22,
    "rotation": 0
  },
  {
    "plane": 0,
    "i": 27,
    "j": 20,
    "x": 8,
    "y": 60,
    "id": 120001,
    "type": 22,
    "rotation": 0
  },
  {
    "plane": 0,
    "i": 27,
    "j": 20,
    "x": 25,
    "y": 49,
    "id": 120001,
    "type": 22,
    "rotation": 3
  },
  {
    "plane": 0,
    "i": 27,
    "j": 20,
    "x": 25,
    "y": 60,
    "id": 120001,
    "type": 22,
    "rotation": 0
  },
  {
    "plane": 0,
    "i": 27,
    "j": 20,
    "x": 33,
    "y": 57,
    "id": 120001,
    "type": 22,
    "rotation": 1
  },
  {
    "plane": 0,
    "i": 27,
    "j": 20,
    "x": 34,
    "y": 44,
    "id": 120001,
    "type": 22,
    "rotation": 3
  },
  {
    "plane": 0,
    "i": 30,
    "j": 22,
    "x": 45,
    "y": 55,
    "id": 120001,
    "type": 22,
    "rotation": 1
  },
  {
    "plane": 0,
    "i": 30,
    "j": 22,
    "x": 48,
    "y": 53,
    "id": 120001,
    "type": 22,
    "rotation": 0
  },
  {
    "plane": 0,
    "i": 30,
    "j": 22,
    "x": 48,
    "y": 54,
    "id": 120001,
    "type": 22,
    "rotation": 1
  },
  {
    "plane": 0,
    "i": 30,
    "j": 22,
    "x": 51,
    "y": 58,
    "id": 120001,
    "type": 22,
    "rotation": 0
  },
  {
    "plane": 0,
    "i": 30,
    "j": 22,
    "x": 54,
    "y": 41,
    "id": 120001,
    "type": 22,
    "rotation": 3
  },
  {
    "plane": 0,
    "i": 30,
    "j": 22,
    "x": 55,
    "y": 29,
    "id": 120001,
    "type": 22,
    "rotation": 1
  },
  {
    "plane": 0,
    "i": 30,
    "j": 22,
    "x": 55,
    "y": 31,
    "id": 120001,
    "type": 22,
    "rotation": 1
  },
  {
    "plane": 0,
    "i": 30,
    "j": 22,
    "x": 55,
    "y": 36,
    "id": 120001,
    "type": 22,
    "rotation": 3
  },
  {
    "plane": 0,
    "i": 30,
    "j": 22,
    "x": 55,
    "y": 42,
    "id": 120001,
    "type": 22,
    "rotation": 3
  },
  {
    "plane": 0,
    "i": 30,
    "j": 22,
    "x": 57,
    "y": 55,
    "id": 120001,
    "type": 22,
    "rotation": 0
  },
  {
    "plane": 0,
    "i": 30,
    "j": 22,
    "x": 60,
    "y": 52,
    "id": 120001,
    "type": 22,
    "rotation": 1
  },
  {
    "plane": 0,
    "i": 30,
    "j": 22,
    "x": 60,
    "y": 55,
    "id": 120001,
    "type": 22,
    "rotation": 1
  },
  {
    "plane": 0,
    "i": 31,
    "j": 22,
    "x": 31,
    "y": 58,
    "id": 120001,
    "type": 22,
    "rotation": 3
  },
  {
    "plane": 0,
    "i": 31,
    "j": 22,
    "x": 33,
    "y": 60,
    "id": 120001,
    "type": 22,
    "rotation": 0
  },
  {
    "plane": 0,
    "i": 31,
    "j": 22,
    "x": 34,
    "y": 48,
    "id": 120001,
    "type": 22,
    "rotation": 3
  },
  {
    "plane": 0,
    "i": 31,
    "j": 22,
    "x": 1,
    "y": 25,
    "id": 120001,
    "type": 22,
    "rotation": 2
  },
  {
    "plane": 0,
    "i": 31,
    "j": 22,
    "x": 3,
    "y": 58,
    "id": 120001,
    "type": 22,
    "rotation": 1
  },
  {
    "plane": 0,
    "i": 31,
    "j": 22,
    "x": 7,
    "y": 29,
    "id": 120001,
    "type": 22,
    "rotation": 0
  },
  {
    "plane": 0,
    "i": 31,
    "j": 22,
    "x": 8,
    "y": 60,
    "id": 120001,
    "type": 22,
    "rotation": 0
  },
  {
    "plane": 0,
    "i": 31,
    "j": 22,
    "x": 9,
    "y": 59,
    "id": 120001,
    "type": 22,
    "rotation": 3
  },
  {
    "plane": 0,
    "i": 31,
    "j": 22,
    "x": 11,
    "y": 52,
    "id": 120001,
    "type": 22,
    "rotation": 0
  },
  {
    "plane": 0,
    "i": 31,
    "j": 22,
    "x": 12,
    "y": 48,
    "id": 120001,
    "type": 22,
    "rotation": 3
  },
  {
    "plane": 0,
    "i": 31,
    "j": 22,
    "x": 14,
    "y": 46,
    "id": 120001,
    "type": 22,
    "rotation": 3
  },
  {
    "plane": 0,
    "i": 31,
    "j": 22,
    "x": 14,
    "y": 47,
    "id": 120001,
    "type": 22,
    "rotation": 2
  },
  {
    "plane": 0,
    "i": 31,
    "j": 22,
    "x": 14,
    "y": 48,
    "id": 120001,
    "type": 22,
    "rotation": 0
  },
  {
    "plane": 0,
    "i": 31,
    "j": 22,
    "x": 14,
    "y": 49,
    "id": 120001,
    "type": 22,
    "rotation": 1
  },
  {
    "plane": 0,
    "i": 31,
    "j": 22,
    "x": 15,
    "y": 52,
    "id": 120001,
    "type": 22,
    "rotation": 3
  },
  {
    "plane": -1,
    "i": 30,
    "j": 23,
    "x": 48,
    "y": 20,
    "id": 120001,
    "type": 22,
    "rotation": 0
  },
  {
    "plane": -1,
    "i": 30,
    "j": 23,
    "x": 49,
    "y": 29,
    "id": 120001,
    "type": 22,
    "rotation": 2
  },
  {
    "plane": -1,
    "i": 30,
    "j": 23,
    "x": 49,
    "y": 30,
    "id": 120001,
    "type": 22,
    "rotation": 1
  },
  {
    "plane": -1,
    "i": 30,
    "j": 23,
    "x": 51,
    "y": 30,
    "id": 120001,
    "type": 22,
    "rotation": 0
  },
  {
    "plane": -1,
    "i": 30,
    "j": 23,
    "x": 56,
    "y": 31,
    "id": 120001,
    "type": 22,
    "rotation": 0
  },
  {
    "plane": -1,
    "i": 30,
    "j": 23,
    "x": 57,
    "y": 18,
    "id": 120001,
    "type": 22,
    "rotation": 2
  },
  {
    "plane": -1,
    "i": 30,
    "j": 23,
    "x": 58,
    "y": 18,
    "id": 120001,
    "type": 22,
    "rotation": 1
  },
  {
    "plane": -1,
    "i": 30,
    "j": 23,
    "x": 59,
    "y": 19,
    "id": 120001,
    "type": 22,
    "rotation": 0
  },
  {
    "plane": -1,
    "i": 30,
    "j": 23,
    "x": 59,
    "y": 30,
    "id": 120001,
    "type": 22,
    "rotation": 1
  },
  {
    "plane": -1,
    "i": 30,
    "j": 23,
    "x": 59,
    "y": 31,
    "id": 120001,
    "type": 22,
    "rotation": 2
  },
  {
    "plane": -1,
    "i": 30,
    "j": 23,
    "x": 60,
    "y": 19,
    "id": 120001,
    "type": 22,
    "rotation": 3
  },
  {
    "plane": -1,
    "i": 30,
    "j": 23,
    "x": 61,
    "y": 19,
    "id": 120001,
    "type": 22,
    "rotation": 2
  },
  {
    "plane": 0,
    "i": 30,
    "j": 23,
    "x": 18,
    "y": 33,
    "id": 120001,
    "type": 22,
    "rotation": 0
  },
  {
    "plane": 0,
    "i": 30,
    "j": 23,
    "x": 27,
    "y": 24,
    "id": 120001,
    "type": 22,
    "rotation": 1
  },
  {
    "plane": 0,
    "i": 30,
    "j": 23,
    "x": 29,
    "y": 33,
    "id": 120001,
    "type": 22,
    "rotation": 2
  },
  {
    "plane": 0,
    "i": 30,
    "j": 23,
    "x": 33,
    "y": 26,
    "id": 120001,
    "type": 22,
    "rotation": 1
  },
  {
    "plane": 0,
    "i": 30,
    "j": 23,
    "x": 34,
    "y": 39,
    "id": 120001,
    "type": 22,
    "rotation": 2
  },
  {
    "plane": 0,
    "i": 30,
    "j": 23,
    "x": 35,
    "y": 41,
    "id": 120001,
    "type": 22,
    "rotation": 2
  },
  {
    "plane": 0,
    "i": 30,
    "j": 23,
    "x": 37,
    "y": 41,
    "id": 120001,
    "type": 22,
    "rotation": 0
  },
  {
    "plane": 0,
    "i": 30,
    "j": 23,
    "x": 40,
    "y": 22,
    "id": 120001,
    "type": 22,
    "rotation": 3
  },
  {
    "plane": 0,
    "i": 30,
    "j": 23,
    "x": 41,
    "y": 30,
    "id": 120001,
    "type": 22,
    "rotation": 2
  },
  {
    "plane": 0,
    "i": 30,
    "j": 23,
    "x": 43,
    "y": 21,
    "id": 120001,
    "type": 22,
    "rotation": 0
  },
  {
    "plane": 0,
    "i": 30,
    "j": 23,
    "x": 44,
    "y": 8,
    "id": 120001,
    "type": 22,
    "rotation": 3
  },
  {
    "plane": 0,
    "i": 30,
    "j": 23,
    "x": 45,
    "y": 35,
    "id": 120001,
    "type": 22,
    "rotation": 0
  },
  {
    "plane": 0,
    "i": 30,
    "j": 23,
    "x": 49,
    "y": 9,
    "id": 120001,
    "type": 22,
    "rotation": 3
  },
  {
    "plane": 0,
    "i": 30,
    "j": 23,
    "x": 53,
    "y": 8,
    "id": 120001,
    "type": 22,
    "rotation": 0
  },
  {
    "plane": 0,
    "i": 30,
    "j": 23,
    "x": 55,
    "y": 9,
    "id": 120001,
    "type": 22,
    "rotation": 0
  },
  {
    "plane": 0,
    "i": 30,
    "j": 23,
    "x": 58,
    "y": 15,
    "id": 120001,
    "type": 22,
    "rotation": 2
  },
  {
    "plane": 0,
    "i": 30,
    "j": 23,
    "x": 59,
    "y": 31,
    "id": 120001,
    "type": 22,
    "rotation": 3
  },
  {
    "plane": 0,
    "i": 30,
    "j": 23,
    "x": 60,
    "y": 27,
    "id": 120001,
    "type": 22,
    "rotation": 0
  },
  {
    "plane": 0,
    "i": 30,
    "j": 23,
    "x": 62,
    "y": 25,
    "id": 120001,
    "type": 22,
    "rotation": 0
  },
  {
    "plane": 0,
    "i": 30,
    "j": 23,
    "x": 63,
    "y": 11,
    "id": 120001,
    "type": 22,
    "rotation": 2
  },
  {
    "plane": 0,
    "i": 30,
    "j": 23,
    "x": 63,
    "y": 14,
    "id": 120001,
    "type": 22,
    "rotation": 1
  },
  {
    "plane": 0,
    "i": 30,
    "j": 23,
    "x": 63,
    "y": 26,
    "id": 120001,
    "type": 22,
    "rotation": 1
  },
  {
    "plane": 0,
    "i": 31,
    "j": 23,
    "x": 1,
    "y": 11,
    "id": 120001,
    "type": 22,
    "rotation": 3
  },
  {
    "plane": 0,
    "i": 31,
    "j": 23,
    "x": 2,
    "y": 12,
    "id": 120001,
    "type": 22,
    "rotation": 2
  },
  {
    "plane": 0,
    "i": 31,
    "j": 23,
    "x": 3,
    "y": 14,
    "id": 120001,
    "type": 22,
    "rotation": 0
  },
  {
    "plane": 0,
    "i": 31,
    "j": 23,
    "x": 4,
    "y": 10,
    "id": 120001,
    "type": 22,
    "rotation": 1
  },
  {
    "plane": 0,
    "i": 31,
    "j": 23,
    "x": 5,
    "y": 10,
    "id": 120001,
    "type": 22,
    "rotation": 2
  },
  {
    "plane": 0,
    "i": 31,
    "j": 23,
    "x": 11,
    "y": 13,
    "id": 120001,
    "type": 22,
    "rotation": 0
  },
  {
    "plane": 0,
    "i": 31,
    "j": 23,
    "x": 11,
    "y": 34,
    "id": 120001,
    "type": 22,
    "rotation": 3
  },
  {
    "plane": 0,
    "i": 31,
    "j": 23,
    "x": 22,
    "y": 11,
    "id": 120001,
    "type": 22,
    "rotation": 2
  },
  {
    "plane": 0,
    "i": 31,
    "j": 23,
    "x": 26,
    "y": 34,
    "id": 120001,
    "type": 22,
    "rotation": 3
  },
  {
    "plane": 0,
    "i": 31,
    "j": 23,
    "x": 28,
    "y": 17,
    "id": 120001,
    "type": 22,
    "rotation": 2
  },
  {
    "plane": 0,
    "i": 31,
    "j": 23,
    "x": 29,
    "y": 18,
    "id": 120001,
    "type": 22,
    "rotation": 1
  },
  {
    "plane": 0,
    "i": 31,
    "j": 23,
    "x": 32,
    "y": 20,
    "id": 120001,
    "type": 22,
    "rotation": 1
  },
  {
    "plane": 0,
    "i": 31,
    "j": 23,
    "x": 33,
    "y": 21,
    "id": 120001,
    "type": 22,
    "rotation": 0
  },
  {
    "plane": 0,
    "i": 31,
    "j": 23,
    "x": 34,
    "y": 11,
    "id": 120001,
    "type": 22,
    "rotation": 1
  },
  {
    "plane": 0,
    "i": 31,
    "j": 23,
    "x": 36,
    "y": 13,
    "id": 120001,
    "type": 22,
    "rotation": 3
  },
  {
    "plane": 0,
    "i": 31,
    "j": 23,
    "x": 36,
    "y": 36,
    "id": 120001,
    "type": 22,
    "rotation": 3
  },
  {
    "plane": 0,
    "i": 31,
    "j": 23,
    "x": 36,
    "y": 38,
    "id": 120001,
    "type": 22,
    "rotation": 0
  },
  {
    "plane": -1,
    "i": 31,
    "j": 23,
    "x": 44,
    "y": 21,
    "id": 120001,
    "type": 22,
    "rotation": 3
  },
  {
    "plane": -1,
    "i": 31,
    "j": 23,
    "x": 45,
    "y": 20,
    "id": 120001,
    "type": 22,
    "rotation": 0
  },
  {
    "plane": -1,
    "i": 31,
    "j": 23,
    "x": 45,
    "y": 21,
    "id": 120001,
    "type": 22,
    "rotation": 2
  },
  {
    "plane": -1,
    "i": 31,
    "j": 23,
    "x": 45,
    "y": 22,
    "id": 120001,
    "type": 22,
    "rotation": 1
  },
  {
    "plane": -1,
    "i": 31,
    "j": 23,
    "x": 47,
    "y": 24,
    "id": 120001,
    "type": 22,
    "rotation": 2
  },
  {
    "plane": 0,
    "i": 31,
    "j": 23,
    "x": 48,
    "y": 3,
    "id": 120001,
    "type": 22,
    "rotation": 0
  },
  {
    "plane": 0,
    "i": 31,
    "j": 23,
    "x": 48,
    "y": 8,
    "id": 120001,
    "type": 22,
    "rotation": 0
  },
  {
    "plane": -1,
    "i": 31,
    "j": 23,
    "x": 48,
    "y": 28,
    "id": 120001,
    "type": 22,
    "rotation": 0
  },
  {
    "plane": 0,
    "i": 31,
    "j": 23,
    "x": 49,
    "y": 4,
    "id": 120001,
    "type": 22,
    "rotation": 3
  },
  {
    "plane": 1,
    "i": 31,
    "j": 23,
    "x": 0,
    "y": 13,
    "id": 120001,
    "type": 22,
    "rotation": 1
  },
  {
    "plane": 1,
    "i": 31,
    "j": 23,
    "x": 0,
    "y": 21,
    "id": 120001,
    "type": 22,
    "rotation": 2
  },
  {
    "plane": 0,
    "i": 31,
    "j": 23,
    "x": 0,
    "y": 36,
    "id": 120001,
    "type": 22,
    "rotation": 2
  },
  {
    "plane": 1,
    "i": 31,
    "j": 23,
    "x": 1,
    "y": 10,
    "id": 120001,
    "type": 22,
    "rotation": 0
  },
  {
    "plane": 1,
    "i": 31,
    "j": 23,
    "x": 1,
    "y": 22,
    "id": 120001,
    "type": 22,
    "rotation": 1
  },
  {
    "plane": 1,
    "i": 31,
    "j": 23,
    "x": 2,
    "y": 23,
    "id": 120001,
    "type": 22,
    "rotation": 2
  },
  {
    "plane": 1,
    "i": 31,
    "j": 23,
    "x": 2,
    "y": 25,
    "id": 120001,
    "type": 22,
    "rotation": 3
  },
  {
    "plane": 0,
    "i": 31,
    "j": 23,
    "x": 6,
    "y": 41,
    "id": 120001,
    "type": 22,
    "rotation": 0
  },
  {
    "plane": 1,
    "i": 31,
    "j": 23,
    "x": 15,
    "y": 9,
    "id": 120001,
    "type": 22,
    "rotation": 1
  },
  {
    "plane": 1,
    "i": 31,
    "j": 23,
    "x": 18,
    "y": 11,
    "id": 120001,
    "type": 22,
    "rotation": 3
  },
  {
    "plane": 0,
    "i": 24,
    "j": 24,
    "x": 20,
    "y": 41,
    "id": 120001,
    "type": 22,
    "rotation": 2
  },
  {
    "plane": 0,
    "i": 25,
    "j": 24,
    "x": 8,
    "y": 58,
    "id": 120001,
    "type": 22,
    "rotation": 3
  },
  {
    "plane": 0,
    "i": 25,
    "j": 24,
    "x": 9,
    "y": 46,
    "id": 120001,
    "type": 22,
    "rotation": 2
  },
  {
    "plane": 0,
    "i": 25,
    "j": 24,
    "x": 9,
    "y": 59,
    "id": 120001,
    "type": 22,
    "rotation": 2
  },
  {
    "plane": 0,
    "i": 25,
    "j": 24,
    "x": 9,
    "y": 61,
    "id": 120001,
    "type": 22,
    "rotation": 0
  },
  {
    "plane": 0,
    "i": 25,
    "j": 24,
    "x": 10,
    "y": 47,
    "id": 120001,
    "type": 22,
    "rotation": 1
  },
  {
    "plane": 0,
    "i": 25,
    "j": 24,
    "x": 10,
    "y": 62,
    "id": 120001,
    "type": 22,
    "rotation": 1
  },
  {
    "plane": 0,
    "i": 25,
    "j": 24,
    "x": 11,
    "y": 55,
    "id": 120001,
    "type": 22,
    "rotation": 0
  },
  {
    "plane": 0,
    "i": 25,
    "j": 24,
    "x": 12,
    "y": 50,
    "id": 120001,
    "type": 22,
    "rotation": 2
  },
  {
    "plane": 0,
    "i": 25,
    "j": 24,
    "x": 13,
    "y": 58,
    "id": 120001,
    "type": 22,
    "rotation": 2
  },
  {
    "plane": 0,
    "i": 25,
    "j": 24,
    "x": 14,
    "y": 45,
    "id": 120001,
    "type": 22,
    "rotation": 1
  },
  {
    "plane": 0,
    "i": 25,
    "j": 24,
    "x": 14,
    "y": 47,
    "id": 120001,
    "type": 22,
    "rotation": 0
  },
  {
    "plane": 0,
    "i": 25,
    "j": 24,
    "x": 14,
    "y": 56,
    "id": 120001,
    "type": 22,
    "rotation": 0
  },
  {
    "plane": -1,
    "i": 25,
    "j": 24,
    "x": 15,
    "y": 55,
    "id": 120001,
    "type": 22,
    "rotation": 2
  },
  {
    "plane": 0,
    "i": 25,
    "j": 24,
    "x": 15,
    "y": 59,
    "id": 120001,
    "type": 22,
    "rotation": 3
  },
  {
    "plane": 0,
    "i": 25,
    "j": 24,
    "x": 15,
    "y": 62,
    "id": 120001,
    "type": 22,
    "rotation": 2
  },
  {
    "plane": -1,
    "i": 25,
    "j": 24,
    "x": 16,
    "y": 55,
    "id": 120001,
    "type": 22,
    "rotation": 2
  },
  {
    "plane": 0,
    "i": 25,
    "j": 24,
    "x": 19,
    "y": 34,
    "id": 120001,
    "type": 22,
    "rotation": 2
  },
  {
    "plane": 0,
    "i": 25,
    "j": 24,
    "x": 20,
    "y": 33,
    "id": 120001,
    "type": 22,
    "rotation": 1
  },
  {
    "plane": 0,
    "i": 25,
    "j": 24,
    "x": 23,
    "y": 32,
    "id": 120001,
    "type": 22,
    "rotation": 3
  },
  {
    "plane": 0,
    "i": 25,
    "j": 24,
    "x": 23,
    "y": 52,
    "id": 120001,
    "type": 22,
    "rotation": 2
  },
  {
    "plane": 0,
    "i": 25,
    "j": 24,
    "x": 23,
    "y": 53,
    "id": 120001,
    "type": 22,
    "rotation": 2
  },
  {
    "plane": 0,
    "i": 25,
    "j": 24,
    "x": 27,
    "y": 49,
    "id": 120001,
    "type": 22,
    "rotation": 1
  },
  {
    "plane": 0,
    "i": 25,
    "j": 24,
    "x": 32,
    "y": 54,
    "id": 120001,
    "type": 22,
    "rotation": 3
  },
  {
    "plane": -1,
    "i": 25,
    "j": 24,
    "x": 32,
    "y": 59,
    "id": 120001,
    "type": 22,
    "rotation": 1
  },
  {
    "plane": -1,
    "i": 25,
    "j": 24,
    "x": 33,
    "y": 60,
    "id": 120001,
    "type": 22,
    "rotation": 2
  },
  {
    "plane": -1,
    "i": 25,
    "j": 24,
    "x": 33,
    "y": 61,
    "id": 120001,
    "type": 22,
    "rotation": 0
  },
  {
    "plane": -1,
    "i": 25,
    "j": 24,
    "x": 35,
    "y": 58,
    "id": 120001,
    "type": 22,
    "rotation": 0
  },
  {
    "plane": 0,
    "i": 25,
    "j": 24,
    "x": 45,
    "y": 55,
    "id": 120001,
    "type": 22,
    "rotation": 2
  },
  {
    "plane": -1,
    "i": 25,
    "j": 24,
    "x": 45,
    "y": 58,
    "id": 120001,
    "type": 22,
    "rotation": 0
  },
  {
    "plane": 0,
    "i": 25,
    "j": 24,
    "x": 46,
    "y": 53,
    "id": 120001,
    "type": 22,
    "rotation": 3
  },
  {
    "plane": 0,
    "i": 25,
    "j": 24,
    "x": 47,
    "y": 59,
    "id": 120001,
    "type": 22,
    "rotation": 2
  },
  {
    "plane": 0,
    "i": 25,
    "j": 24,
    "x": 48,
    "y": 52,
    "id": 120001,
    "type": 22,
    "rotation": 1
  },
  {
    "plane": 0,
    "i": 25,
    "j": 24,
    "x": 48,
    "y": 53,
    "id": 120001,
    "type": 22,
    "rotation": 2
  },
  {
    "plane": 0,
    "i": 25,
    "j": 24,
    "x": 48,
    "y": 61,
    "id": 120001,
    "type": 22,
    "rotation": 3
  },
  {
    "plane": 0,
    "i": 25,
    "j": 24,
    "x": 49,
    "y": 32,
    "id": 120001,
    "type": 22,
    "rotation": 1
  },
  {
    "plane": 0,
    "i": 25,
    "j": 24,
    "x": 49,
    "y": 45,
    "id": 120001,
    "type": 22,
    "rotation": 1
  },
  {
    "plane": 0,
    "i": 25,
    "j": 24,
    "x": 50,
    "y": 34,
    "id": 120001,
    "type": 22,
    "rotation": 2
  },
  {
    "plane": 0,
    "i": 25,
    "j": 24,
    "x": 50,
    "y": 53,
    "id": 120001,
    "type": 22,
    "rotation": 3
  },
  {
    "plane": 0,
    "i": 25,
    "j": 24,
    "x": 51,
    "y": 45,
    "id": 120001,
    "type": 22,
    "rotation": 1
  },
  {
    "plane": 0,
    "i": 25,
    "j": 24,
    "x": 51,
    "y": 54,
    "id": 120001,
    "type": 22,
    "rotation": 2
  },
  {
    "plane": 0,
    "i": 25,
    "j": 24,
    "x": 52,
    "y": 46,
    "id": 120001,
    "type": 22,
    "rotation": 3
  },
  {
    "plane": 0,
    "i": 25,
    "j": 24,
    "x": 58,
    "y": 41,
    "id": 120001,
    "type": 22,
    "rotation": 0
  },
  {
    "plane": 0,
    "i": 25,
    "j": 24,
    "x": 58,
    "y": 42,
    "id": 120001,
    "type": 22,
    "rotation": 2
  },
  {
    "plane": 0,
    "i": 25,
    "j": 24,
    "x": 58,
    "y": 50,
    "id": 120001,
    "type": 22,
    "rotation": 2
  },
  {
    "plane": 0,
    "i": 25,
    "j": 24,
    "x": 59,
    "y": 36,
    "id": 120001,
    "type": 22,
    "rotation": 2
  },
  {
    "plane": 0,
    "i": 25,
    "j": 24,
    "x": 59,
    "y": 39,
    "id": 120001,
    "type": 22,
    "rotation": 1
  },
  {
    "plane": 0,
    "i": 25,
    "j": 24,
    "x": 59,
    "y": 60,
    "id": 120001,
    "type": 22,
    "rotation": 1
  },
  {
    "plane": 0,
    "i": 25,
    "j": 24,
    "x": 60,
    "y": 43,
    "id": 120001,
    "type": 22,
    "rotation": 0
  },
  {
    "plane": 0,
    "i": 25,
    "j": 24,
    "x": 18,
    "y": 61,
    "id": 120001,
    "type": 22,
    "rotation": 2
  },
  {
    "plane": 0,
    "i": 25,
    "j": 24,
    "x": 19,
    "y": 62,
    "id": 120001,
    "type": 22,
    "rotation": 1
  },
  {
    "plane": 0,
    "i": 25,
    "j": 24,
    "x": 62,
    "y": 28,
    "id": 120001,
    "type": 22,
    "rotation": 1
  },
  {
    "plane": 0,
    "i": 25,
    "j": 24,
    "x": 63,
    "y": 29,
    "id": 120001,
    "type": 22,
    "rotation": 2
  },
  {
    "plane": 0,
    "i": 26,
    "j": 24,
    "x": 5,
    "y": 59,
    "id": 120001,
    "type": 22,
    "rotation": 2
  },
  {
    "plane": 0,
    "i": 26,
    "j": 24,
    "x": 6,
    "y": 45,
    "id": 120001,
    "type": 22,
    "rotation": 2
  },
  {
    "plane": 0,
    "i": 26,
    "j": 24,
    "x": 6,
    "y": 60,
    "id": 120001,
    "type": 22,
    "rotation": 2
  },
  {
    "plane": 0,
    "i": 26,
    "j": 24,
    "x": 7,
    "y": 50,
    "id": 120001,
    "type": 22,
    "rotation": 1
  },
  {
    "plane": 0,
    "i": 26,
    "j": 24,
    "x": 8,
    "y": 33,
    "id": 120001,
    "type": 22,
    "rotation": 3
  },
  {
    "plane": 0,
    "i": 26,
    "j": 24,
    "x": 10,
    "y": 43,
    "id": 120001,
    "type": 22,
    "rotation": 2
  },
  {
    "plane": 0,
    "i": 26,
    "j": 24,
    "x": 10,
    "y": 57,
    "id": 120001,
    "type": 22,
    "rotation": 2
  },
  {
    "plane": 0,
    "i": 26,
    "j": 24,
    "x": 11,
    "y": 45,
    "id": 120001,
    "type": 22,
    "rotation": 3
  },
  {
    "plane": 0,
    "i": 26,
    "j": 24,
    "x": 12,
    "y": 47,
    "id": 120001,
    "type": 22,
    "rotation": 2
  },
  {
    "plane": 0,
    "i": 26,
    "j": 24,
    "x": 13,
    "y": 33,
    "id": 120001,
    "type": 22,
    "rotation": 1
  },
  {
    "plane": 0,
    "i": 26,
    "j": 24,
    "x": 13,
    "y": 58,
    "id": 120001,
    "type": 22,
    "rotation": 0
  },
  {
    "plane": 0,
    "i": 26,
    "j": 24,
    "x": 14,
    "y": 57,
    "id": 120001,
    "type": 22,
    "rotation": 2
  },
  {
    "plane": 0,
    "i": 26,
    "j": 24,
    "x": 15,
    "y": 35,
    "id": 120001,
    "type": 22,
    "rotation": 0
  },
  {
    "plane": 0,
    "i": 26,
    "j": 24,
    "x": 18,
    "y": 50,
    "id": 120001,
    "type": 22,
    "rotation": 1
  },
  {
    "plane": 0,
    "i": 26,
    "j": 24,
    "x": 18,
    "y": 55,
    "id": 120001,
    "type": 22,
    "rotation": 0
  },
  {
    "plane": 0,
    "i": 26,
    "j": 24,
    "x": 19,
    "y": 39,
    "id": 120001,
    "type": 22,
    "rotation": 1
  },
  {
    "plane": 0,
    "i": 26,
    "j": 24,
    "x": 19,
    "y": 58,
    "id": 120001,
    "type": 22,
    "rotation": 3
  },
  {
    "plane": 0,
    "i": 26,
    "j": 24,
    "x": 21,
    "y": 50,
    "id": 120001,
    "type": 22,
    "rotation": 3
  },
  {
    "plane": 0,
    "i": 26,
    "j": 24,
    "x": 22,
    "y": 53,
    "id": 120001,
    "type": 22,
    "rotation": 3
  },
  {
    "plane": 0,
    "i": 26,
    "j": 24,
    "x": 23,
    "y": 47,
    "id": 120001,
    "type": 22,
    "rotation": 0
  },
  {
    "plane": 0,
    "i": 26,
    "j": 24,
    "x": 24,
    "y": 46,
    "id": 120001,
    "type": 22,
    "rotation": 0
  },
  {
    "plane": 0,
    "i": 26,
    "j": 24,
    "x": 27,
    "y": 47,
    "id": 120001,
    "type": 22,
    "rotation": 0
  },
  {
    "plane": 0,
    "i": 26,
    "j": 24,
    "x": 27,
    "y": 52,
    "id": 120001,
    "type": 22,
    "rotation": 3
  },
  {
    "plane": 0,
    "i": 26,
    "j": 24,
    "x": 28,
    "y": 61,
    "id": 120001,
    "type": 22,
    "rotation": 2
  },
  {
    "plane": 0,
    "i": 26,
    "j": 24,
    "x": 29,
    "y": 47,
    "id": 120001,
    "type": 22,
    "rotation": 1
  },
  {
    "plane": 0,
    "i": 26,
    "j": 24,
    "x": 36,
    "y": 62,
    "id": 120001,
    "type": 22,
    "rotation": 1
  },
  {
    "plane": 0,
    "i": 26,
    "j": 24,
    "x": 38,
    "y": 63,
    "id": 120001,
    "type": 22,
    "rotation": 2
  },
  {
    "plane": 0,
    "i": 26,
    "j": 24,
    "x": 49,
    "y": 61,
    "id": 120001,
    "type": 22,
    "rotation": 1
  },
  {
    "plane": 0,
    "i": 26,
    "j": 24,
    "x": 49,
    "y": 62,
    "id": 120001,
    "type": 22,
    "rotation": 2
  },
  {
    "plane": 0,
    "i": 26,
    "j": 24,
    "x": 51,
    "y": 61,
    "id": 120001,
    "type": 22,
    "rotation": 0
  },
  {
    "plane": 0,
    "i": 26,
    "j": 24,
    "x": 3,
    "y": 24,
    "id": 120001,
    "type": 22,
    "rotation": 3
  },
  {
    "plane": 1,
    "i": 26,
    "j": 24,
    "x": 13,
    "y": 47,
    "id": 120001,
    "type": 22,
    "rotation": 3
  },
  {
    "plane": 1,
    "i": 26,
    "j": 24,
    "x": 15,
    "y": 46,
    "id": 120001,
    "type": 22,
    "rotation": 2
  },
  {
    "plane": 1,
    "i": 26,
    "j": 24,
    "x": 19,
    "y": 46,
    "id": 120001,
    "type": 22,
    "rotation": 0
  },
  {
    "plane": 0,
    "i": 28,
    "j": 24,
    "x": 20,
    "y": 41,
    "id": 120001,
    "type": 22,
    "rotation": 2
  },
  {
    "plane": 0,
    "i": 24,
    "j": 25,
    "x": 20,
    "y": 41,
    "id": 120001,
    "type": 22,
    "rotation": 2
  },
  {
    "plane": 0,
    "i": 25,
    "j": 25,
    "x": 6,
    "y": 12,
    "id": 120001,
    "type": 22,
    "rotation": 3
  },
  {
    "plane": 0,
    "i": 25,
    "j": 25,
    "x": 7,
    "y": 6,
    "id": 120001,
    "type": 22,
    "rotation": 2
  },
  {
    "plane": 0,
    "i": 25,
    "j": 25,
    "x": 7,
    "y": 8,
    "id": 120001,
    "type": 22,
    "rotation": 2
  },
  {
    "plane": 0,
    "i": 25,
    "j": 25,
    "x": 9,
    "y": 9,
    "id": 120001,
    "type": 22,
    "rotation": 0
  },
  {
    "plane": 0,
    "i": 25,
    "j": 25,
    "x": 9,
    "y": 19,
    "id": 120001,
    "type": 22,
    "rotation": 0
  },
  {
    "plane": 0,
    "i": 25,
    "j": 25,
    "x": 9,
    "y": 30,
    "id": 120001,
    "type": 22,
    "rotation": 2
  },
  {
    "plane": 0,
    "i": 25,
    "j": 25,
    "x": 9,
    "y": 45,
    "id": 120001,
    "type": 22,
    "rotation": 2
  },
  {
    "plane": 0,
    "i": 25,
    "j": 25,
    "x": 9,
    "y": 47,
    "id": 120001,
    "type": 22,
    "rotation": 1
  },
  {
    "plane": 0,
    "i": 25,
    "j": 25,
    "x": 10,
    "y": 1,
    "id": 120001,
    "type": 22,
    "rotation": 3
  },
  {
    "plane": 0,
    "i": 25,
    "j": 25,
    "x": 11,
    "y": 31,
    "id": 120001,
    "type": 22,
    "rotation": 1
  },
  {
    "plane": 0,
    "i": 25,
    "j": 25,
    "x": 11,
    "y": 40,
    "id": 120001,
    "type": 22,
    "rotation": 3
  },
  {
    "plane": 0,
    "i": 25,
    "j": 25,
    "x": 11,
    "y": 63,
    "id": 120001,
    "type": 22,
    "rotation": 0
  },
  {
    "plane": 0,
    "i": 25,
    "j": 25,
    "x": 12,
    "y": 14,
    "id": 120001,
    "type": 22,
    "rotation": 3
  },
  {
    "plane": 0,
    "i": 25,
    "j": 25,
    "x": 12,
    "y": 20,
    "id": 120001,
    "type": 22,
    "rotation": 1
  },
  {
    "plane": 0,
    "i": 25,
    "j": 25,
    "x": 12,
    "y": 63,
    "id": 120001,
    "type": 22,
    "rotation": 3
  },
  {
    "plane": 0,
    "i": 25,
    "j": 25,
    "x": 13,
    "y": 8,
    "id": 120001,
    "type": 22,
    "rotation": 0
  },
  {
    "plane": 0,
    "i": 25,
    "j": 25,
    "x": 13,
    "y": 12,
    "id": 120001,
    "type": 22,
    "rotation": 1
  },
  {
    "plane": 0,
    "i": 25,
    "j": 25,
    "x": 13,
    "y": 59,
    "id": 120001,
    "type": 22,
    "rotation": 3
  },
  {
    "plane": 0,
    "i": 25,
    "j": 25,
    "x": 14,
    "y": 13,
    "id": 120001,
    "type": 22,
    "rotation": 3
  },
  {
    "plane": 0,
    "i": 25,
    "j": 25,
    "x": 14,
    "y": 19,
    "id": 120001,
    "type": 22,
    "rotation": 0
  },
  {
    "plane": 0,
    "i": 25,
    "j": 25,
    "x": 15,
    "y": 29,
    "id": 120001,
    "type": 22,
    "rotation": 2
  },
  {
    "plane": 0,
    "i": 25,
    "j": 25,
    "x": 17,
    "y": 14,
    "id": 120001,
    "type": 22,
    "rotation": 1
  },
  {
    "plane": 0,
    "i": 25,
    "j": 25,
    "x": 17,
    "y": 35,
    "id": 120001,
    "type": 22,
    "rotation": 3
  },
  {
    "plane": 0,
    "i": 25,
    "j": 25,
    "x": 18,
    "y": 34,
    "id": 120001,
    "type": 22,
    "rotation": 3
  },
  {
    "plane": 0,
    "i": 25,
    "j": 25,
    "x": 18,
    "y": 55,
    "id": 120001,
    "type": 22,
    "rotation": 0
  },
  {
    "plane": 0,
    "i": 25,
    "j": 25,
    "x": 19,
    "y": 35,
    "id": 120001,
    "type": 22,
    "rotation": 1
  },
  {
    "plane": 0,
    "i": 25,
    "j": 25,
    "x": 26,
    "y": 3,
    "id": 120001,
    "type": 22,
    "rotation": 0
  },
  {
    "plane": 0,
    "i": 25,
    "j": 25,
    "x": 27,
    "y": 2,
    "id": 120001,
    "type": 22,
    "rotation": 3
  },
  {
    "plane": 0,
    "i": 25,
    "j": 25,
    "x": 27,
    "y": 13,
    "id": 120001,
    "type": 22,
    "rotation": 0
  },
  {
    "plane": 0,
    "i": 25,
    "j": 25,
    "x": 28,
    "y": 12,
    "id": 120001,
    "type": 22,
    "rotation": 3
  },
  {
    "plane": 0,
    "i": 25,
    "j": 25,
    "x": 29,
    "y": 62,
    "id": 120001,
    "type": 22,
    "rotation": 2
  },
  {
    "plane": -1,
    "i": 25,
    "j": 25,
    "x": 30,
    "y": 1,
    "id": 120001,
    "type": 22,
    "rotation": 1
  },
  {
    "plane": 0,
    "i": 25,
    "j": 25,
    "x": 34,
    "y": 1,
    "id": 120001,
    "type": 22,
    "rotation": 1
  },
  {
    "plane": 0,
    "i": 25,
    "j": 25,
    "x": 34,
    "y": 13,
    "id": 120001,
    "type": 22,
    "rotation": 1
  },
  {
    "plane": 0,
    "i": 25,
    "j": 25,
    "x": 34,
    "y": 20,
    "id": 120001,
    "type": 22,
    "rotation": 1
  },
  {
    "plane": 0,
    "i": 25,
    "j": 25,
    "x": 35,
    "y": 5,
    "id": 120001,
    "type": 22,
    "rotation": 2
  },
  {
    "plane": 0,
    "i": 25,
    "j": 25,
    "x": 36,
    "y": 19,
    "id": 120001,
    "type": 22,
    "rotation": 2
  },
  {
    "plane": 0,
    "i": 25,
    "j": 25,
    "x": 37,
    "y": 51,
    "id": 120001,
    "type": 22,
    "rotation": 1
  },
  {
    "plane": 0,
    "i": 25,
    "j": 25,
    "x": 38,
    "y": 10,
    "id": 120001,
    "type": 22,
    "rotation": 1
  },
  {
    "plane": 0,
    "i": 25,
    "j": 25,
    "x": 38,
    "y": 59,
    "id": 120001,
    "type": 22,
    "rotation": 2
  },
  {
    "plane": 0,
    "i": 25,
    "j": 25,
    "x": 38,
    "y": 60,
    "id": 120001,
    "type": 22,
    "rotation": 2
  },
  {
    "plane": 0,
    "i": 25,
    "j": 25,
    "x": 39,
    "y": 9,
    "id": 120001,
    "type": 22,
    "rotation": 1
  },
  {
    "plane": 0,
    "i": 25,
    "j": 25,
    "x": 40,
    "y": 4,
    "id": 120001,
    "type": 22,
    "rotation": 3
  },
  {
    "plane": 0,
    "i": 25,
    "j": 25,
    "x": 40,
    "y": 8,
    "id": 120001,
    "type": 22,
    "rotation": 0
  },
  {
    "plane": 0,
    "i": 25,
    "j": 25,
    "x": 40,
    "y": 14,
    "id": 120001,
    "type": 22,
    "rotation": 3
  },
  {
    "plane": 0,
    "i": 25,
    "j": 25,
    "x": 41,
    "y": 9,
    "id": 120001,
    "type": 22,
    "rotation": 1
  },
  {
    "plane": 0,
    "i": 25,
    "j": 25,
    "x": 42,
    "y": 0,
    "id": 120001,
    "type": 22,
    "rotation": 2
  },
  {
    "plane": 0,
    "i": 25,
    "j": 25,
    "x": 42,
    "y": 10,
    "id": 120001,
    "type": 22,
    "rotation": 1
  },
  {
    "plane": 0,
    "i": 25,
    "j": 25,
    "x": 43,
    "y": 5,
    "id": 120001,
    "type": 22,
    "rotation": 2
  },
  {
    "plane": 0,
    "i": 25,
    "j": 25,
    "x": 43,
    "y": 56,
    "id": 120001,
    "type": 22,
    "rotation": 3
  },
  {
    "plane": 0,
    "i": 25,
    "j": 25,
    "x": 43,
    "y": 58,
    "id": 120001,
    "type": 22,
    "rotation": 2
  },
  {
    "plane": 0,
    "i": 25,
    "j": 25,
    "x": 43,
    "y": 61,
    "id": 120001,
    "type": 22,
    "rotation": 1
  },
  {
    "plane": 0,
    "i": 25,
    "j": 25,
    "x": 49,
    "y": 5,
    "id": 120001,
    "type": 22,
    "rotation": 2
  },
  {
    "plane": 0,
    "i": 25,
    "j": 25,
    "x": 50,
    "y": 2,
    "id": 120001,
    "type": 22,
    "rotation": 3
  },
  {
    "plane": 0,
    "i": 25,
    "j": 25,
    "x": 50,
    "y": 60,
    "id": 120001,
    "type": 22,
    "rotation": 3
  },
  {
    "plane": 0,
    "i": 25,
    "j": 25,
    "x": 51,
    "y": 57,
    "id": 120001,
    "type": 22,
    "rotation": 3
  },
  {
    "plane": 0,
    "i": 25,
    "j": 25,
    "x": 52,
    "y": 16,
    "id": 120001,
    "type": 22,
    "rotation": 1
  },
  {
    "plane": 0,
    "i": 25,
    "j": 25,
    "x": 52,
    "y": 60,
    "id": 120001,
    "type": 22,
    "rotation": 2
  },
  {
    "plane": 0,
    "i": 25,
    "j": 25,
    "x": 55,
    "y": 48,
    "id": 120001,
    "type": 22,
    "rotation": 2
  },
  {
    "plane": 0,
    "i": 25,
    "j": 25,
    "x": 55,
    "y": 52,
    "id": 120001,
    "type": 22,
    "rotation": 2
  },
  {
    "plane": 0,
    "i": 25,
    "j": 25,
    "x": 55,
    "y": 54,
    "id": 120001,
    "type": 22,
    "rotation": 2
  },
  {
    "plane": 0,
    "i": 25,
    "j": 25,
    "x": 55,
    "y": 57,
    "id": 120001,
    "type": 22,
    "rotation": 2
  },
  {
    "plane": 0,
    "i": 25,
    "j": 25,
    "x": 58,
    "y": 0,
    "id": 120001,
    "type": 22,
    "rotation": 3
  },
  {
    "plane": 0,
    "i": 25,
    "j": 25,
    "x": 58,
    "y": 14,
    "id": 120001,
    "type": 22,
    "rotation": 1
  },
  {
    "plane": 0,
    "i": 25,
    "j": 25,
    "x": 58,
    "y": 20,
    "id": 120001,
    "type": 22,
    "rotation": 1
  },
  {
    "plane": 0,
    "i": 25,
    "j": 25,
    "x": 58,
    "y": 48,
    "id": 120001,
    "type": 22,
    "rotation": 1
  },
  {
    "plane": 0,
    "i": 25,
    "j": 25,
    "x": 59,
    "y": 2,
    "id": 120001,
    "type": 22,
    "rotation": 0
  },
  {
    "plane": 0,
    "i": 25,
    "j": 25,
    "x": 59,
    "y": 13,
    "id": 120001,
    "type": 22,
    "rotation": 0
  },
  {
    "plane": 0,
    "i": 25,
    "j": 25,
    "x": 59,
    "y": 46,
    "id": 120001,
    "type": 22,
    "rotation": 3
  },
  {
    "plane": 0,
    "i": 25,
    "j": 25,
    "x": 60,
    "y": 15,
    "id": 120001,
    "type": 22,
    "rotation": 0
  },
  {
    "plane": 0,
    "i": 25,
    "j": 25,
    "x": 63,
    "y": 20,
    "id": 120001,
    "type": 22,
    "rotation": 0
  },
  {
    "plane": 1,
    "i": 25,
    "j": 25,
    "x": 10,
    "y": 33,
    "id": 120001,
    "type": 22,
    "rotation": 1
  },
  {
    "plane": 1,
    "i": 25,
    "j": 25,
    "x": 10,
    "y": 34,
    "id": 120001,
    "type": 22,
    "rotation": 2
  },
  {
    "plane": 1,
    "i": 25,
    "j": 25,
    "x": 12,
    "y": 30,
    "id": 120001,
    "type": 22,
    "rotation": 0
  },
  {
    "plane": 1,
    "i": 25,
    "j": 25,
    "x": 13,
    "y": 8,
    "id": 120001,
    "type": 22,
    "rotation": 2
  },
  {
    "plane": 1,
    "i": 25,
    "j": 25,
    "x": 46,
    "y": 49,
    "id": 120001,
    "type": 22,
    "rotation": 1
  },
  {
    "plane": 1,
    "i": 25,
    "j": 25,
    "x": 47,
    "y": 52,
    "id": 120001,
    "type": 22,
    "rotation": 0
  },
  {
    "plane": 0,
    "i": 25,
    "j": 25,
    "x": 55,
    "y": 38,
    "id": 120001,
    "type": 22,
    "rotation": 2
  },
  {
    "plane": 0,
    "i": 25,
    "j": 25,
    "x": 56,
    "y": 39,
    "id": 120001,
    "type": 22,
    "rotation": 2
  },
  {
    "plane": 0,
    "i": 26,
    "j": 25,
    "x": 1,
    "y": 30,
    "id": 120001,
    "type": 22,
    "rotation": 3
  },
  {
    "plane": 0,
    "i": 26,
    "j": 25,
    "x": 1,
    "y": 35,
    "id": 120001,
    "type": 22,
    "rotation": 2
  },
  {
    "plane": 0,
    "i": 26,
    "j": 25,
    "x": 2,
    "y": 24,
    "id": 120001,
    "type": 22,
    "rotation": 3
  },
  {
    "plane": 0,
    "i": 26,
    "j": 25,
    "x": 2,
    "y": 29,
    "id": 120001,
    "type": 22,
    "rotation": 2
  },
  {
    "plane": 0,
    "i": 26,
    "j": 25,
    "x": 2,
    "y": 51,
    "id": 120001,
    "type": 22,
    "rotation": 1
  },
  {
    "plane": 0,
    "i": 26,
    "j": 25,
    "x": 3,
    "y": 22,
    "id": 120001,
    "type": 22,
    "rotation": 1
  },
  {
    "plane": 0,
    "i": 26,
    "j": 25,
    "x": 3,
    "y": 29,
    "id": 120001,
    "type": 22,
    "rotation": 1
  },
  {
    "plane": 0,
    "i": 26,
    "j": 25,
    "x": 4,
    "y": 15,
    "id": 120001,
    "type": 22,
    "rotation": 2
  },
  {
    "plane": 0,
    "i": 26,
    "j": 25,
    "x": 4,
    "y": 37,
    "id": 120001,
    "type": 22,
    "rotation": 1
  },
  {
    "plane": 0,
    "i": 26,
    "j": 25,
    "x": 4,
    "y": 41,
    "id": 120001,
    "type": 22,
    "rotation": 1
  },
  {
    "plane": 0,
    "i": 26,
    "j": 25,
    "x": 4,
    "y": 44,
    "id": 120001,
    "type": 22,
    "rotation": 0
  },
  {
    "plane": 0,
    "i": 26,
    "j": 25,
    "x": 4,
    "y": 48,
    "id": 120001,
    "type": 22,
    "rotation": 0
  },
  {
    "plane": 0,
    "i": 26,
    "j": 25,
    "x": 4,
    "y": 51,
    "id": 120001,
    "type": 22,
    "rotation": 0
  },
  {
    "plane": 0,
    "i": 26,
    "j": 25,
    "x": 4,
    "y": 53,
    "id": 120001,
    "type": 22,
    "rotation": 1
  },
  {
    "plane": 0,
    "i": 26,
    "j": 25,
    "x": 4,
    "y": 59,
    "id": 120001,
    "type": 22,
    "rotation": 0
  },
  {
    "plane": 0,
    "i": 26,
    "j": 25,
    "x": 5,
    "y": 25,
    "id": 120001,
    "type": 22,
    "rotation": 0
  },
  {
    "plane": 0,
    "i": 26,
    "j": 25,
    "x": 5,
    "y": 37,
    "id": 120001,
    "type": 22,
    "rotation": 1
  },
  {
    "plane": 0,
    "i": 26,
    "j": 25,
    "x": 5,
    "y": 44,
    "id": 120001,
    "type": 22,
    "rotation": 3
  },
  {
    "plane": 0,
    "i": 26,
    "j": 25,
    "x": 5,
    "y": 50,
    "id": 120001,
    "type": 22,
    "rotation": 3
  },
  {
    "plane": 0,
    "i": 26,
    "j": 25,
    "x": 5,
    "y": 54,
    "id": 120001,
    "type": 22,
    "rotation": 2
  },
  {
    "plane": 0,
    "i": 26,
    "j": 25,
    "x": 6,
    "y": 47,
    "id": 120001,
    "type": 22,
    "rotation": 3
  },
  {
    "plane": 0,
    "i": 26,
    "j": 25,
    "x": 6,
    "y": 55,
    "id": 120001,
    "type": 22,
    "rotation": 3
  },
  {
    "plane": 0,
    "i": 26,
    "j": 25,
    "x": 9,
    "y": 7,
    "id": 120001,
    "type": 22,
    "rotation": 3
  },
  {
    "plane": 0,
    "i": 26,
    "j": 25,
    "x": 9,
    "y": 32,
    "id": 120001,
    "type": 22,
    "rotation": 2
  },
  {
    "plane": 0,
    "i": 26,
    "j": 25,
    "x": 9,
    "y": 34,
    "id": 120001,
    "type": 22,
    "rotation": 1
  },
  {
    "plane": 0,
    "i": 26,
    "j": 25,
    "x": 11,
    "y": 60,
    "id": 120001,
    "type": 22,
    "rotation": 2
  },
  {
    "plane": 0,
    "i": 26,
    "j": 25,
    "x": 11,
    "y": 63,
    "id": 120001,
    "type": 22,
    "rotation": 0
  },
  {
    "plane": 0,
    "i": 26,
    "j": 25,
    "x": 12,
    "y": 5,
    "id": 120001,
    "type": 22,
    "rotation": 1
  },
  {
    "plane": 0,
    "i": 26,
    "j": 25,
    "x": 12,
    "y": 24,
    "id": 120001,
    "type": 22,
    "rotation": 1
  },
  {
    "plane": 0,
    "i": 26,
    "j": 25,
    "x": 14,
    "y": 4,
    "id": 120001,
    "type": 22,
    "rotation": 0
  },
  {
    "plane": 0,
    "i": 26,
    "j": 25,
    "x": 14,
    "y": 6,
    "id": 120001,
    "type": 22,
    "rotation": 3
  },
  {
    "plane": 0,
    "i": 26,
    "j": 25,
    "x": 14,
    "y": 7,
    "id": 120001,
    "type": 22,
    "rotation": 2
  },
  {
    "plane": 0,
    "i": 26,
    "j": 25,
    "x": 15,
    "y": 45,
    "id": 120001,
    "type": 22,
    "rotation": 1
  },
  {
    "plane": 0,
    "i": 26,
    "j": 25,
    "x": 23,
    "y": 21,
    "id": 120001,
    "type": 22,
    "rotation": 1
  },
  {
    "plane": 0,
    "i": 26,
    "j": 25,
    "x": 30,
    "y": 59,
    "id": 120001,
    "type": 22,
    "rotation": 3
  },
  {
    "plane": 0,
    "i": 26,
    "j": 25,
    "x": 33,
    "y": 1,
    "id": 120001,
    "type": 22,
    "rotation": 3
  },
  {
    "plane": 0,
    "i": 26,
    "j": 25,
    "x": 34,
    "y": 2,
    "id": 120001,
    "type": 22,
    "rotation": 1
  },
  {
    "plane": 0,
    "i": 26,
    "j": 25,
    "x": 34,
    "y": 14,
    "id": 120001,
    "type": 22,
    "rotation": 2
  },
  {
    "plane": 0,
    "i": 26,
    "j": 25,
    "x": 35,
    "y": 13,
    "id": 120001,
    "type": 22,
    "rotation": 3
  },
  {
    "plane": 0,
    "i": 26,
    "j": 25,
    "x": 36,
    "y": 20,
    "id": 120001,
    "type": 22,
    "rotation": 0
  },
  {
    "plane": 0,
    "i": 26,
    "j": 25,
    "x": 39,
    "y": 14,
    "id": 120001,
    "type": 22,
    "rotation": 3
  },
  {
    "plane": 0,
    "i": 26,
    "j": 25,
    "x": 40,
    "y": 11,
    "id": 120001,
    "type": 22,
    "rotation": 2
  },
  {
    "plane": 0,
    "i": 26,
    "j": 25,
    "x": 41,
    "y": 34,
    "id": 120001,
    "type": 22,
    "rotation": 1
  },
  {
    "plane": 0,
    "i": 26,
    "j": 25,
    "x": 42,
    "y": 7,
    "id": 120001,
    "type": 22,
    "rotation": 2
  },
  {
    "plane": 0,
    "i": 26,
    "j": 25,
    "x": 42,
    "y": 59,
    "id": 120001,
    "type": 22,
    "rotation": 0
  },
  {
    "plane": 0,
    "i": 26,
    "j": 25,
    "x": 43,
    "y": 9,
    "id": 120001,
    "type": 22,
    "rotation": 0
  },
  {
    "plane": 0,
    "i": 26,
    "j": 25,
    "x": 44,
    "y": 8,
    "id": 120001,
    "type": 22,
    "rotation": 3
  },
  {
    "plane": 0,
    "i": 26,
    "j": 25,
    "x": 45,
    "y": 3,
    "id": 120001,
    "type": 22,
    "rotation": 0
  },
  {
    "plane": 0,
    "i": 26,
    "j": 25,
    "x": 47,
    "y": 19,
    "id": 120001,
    "type": 22,
    "rotation": 1
  },
  {
    "plane": 0,
    "i": 26,
    "j": 25,
    "x": 48,
    "y": 13,
    "id": 120001,
    "type": 22,
    "rotation": 2
  },
  {
    "plane": 0,
    "i": 26,
    "j": 25,
    "x": 48,
    "y": 18,
    "id": 120001,
    "type": 22,
    "rotation": 2
  },
  {
    "plane": 0,
    "i": 26,
    "j": 25,
    "x": 53,
    "y": 16,
    "id": 120001,
    "type": 22,
    "rotation": 2
  },
  {
    "plane": 0,
    "i": 26,
    "j": 25,
    "x": 56,
    "y": 42,
    "id": 120001,
    "type": 22,
    "rotation": 1
  },
  {
    "plane": 0,
    "i": 26,
    "j": 25,
    "x": 56,
    "y": 55,
    "id": 120001,
    "type": 22,
    "rotation": 2
  },
  {
    "plane": 0,
    "i": 26,
    "j": 25,
    "x": 57,
    "y": 39,
    "id": 120001,
    "type": 22,
    "rotation": 2
  },
  {
    "plane": 0,
    "i": 26,
    "j": 25,
    "x": 57,
    "y": 40,
    "id": 120001,
    "type": 22,
    "rotation": 3
  },
  {
    "plane": 0,
    "i": 26,
    "j": 25,
    "x": 2,
    "y": 17,
    "id": 120001,
    "type": 22,
    "rotation": 3
  },
  {
    "plane": 0,
    "i": 26,
    "j": 25,
    "x": 3,
    "y": 25,
    "id": 120001,
    "type": 22,
    "rotation": 0
  },
  {
    "plane": 1,
    "i": 26,
    "j": 25,
    "x": 12,
    "y": 33,
    "id": 120001,
    "type": 22,
    "rotation": 3
  },
  {
    "plane": 1,
    "i": 26,
    "j": 25,
    "x": 17,
    "y": 34,
    "id": 120001,
    "type": 22,
    "rotation": 0
  },
  {
    "plane": 1,
    "i": 26,
    "j": 25,
    "x": 23,
    "y": 30,
    "id": 120001,
    "type": 22,
    "rotation": 3
  },
  {
    "plane": 1,
    "i": 26,
    "j": 25,
    "x": 28,
    "y": 31,
    "id": 120001,
    "type": 22,
    "rotation": 1
  },
  {
    "plane": 1,
    "i": 26,
    "j": 25,
    "x": 44,
    "y": 49,
    "id": 120001,
    "type": 22,
    "rotation": 3
  },
  {
    "plane": 1,
    "i": 26,
    "j": 25,
    "x": 46,
    "y": 58,
    "id": 120001,
    "type": 22,
    "rotation": 3
  },
  {
    "plane": 1,
    "i": 26,
    "j": 25,
    "x": 55,
    "y": 1,
    "id": 120001,
    "type": 22,
    "rotation": 3
  },
  {
    "plane": 1,
    "i": 26,
    "j": 25,
    "x": 57,
    "y": 17,
    "id": 120001,
    "type": 22,
    "rotation": 2
  },
  {
    "plane": 2,
    "i": 26,
    "j": 25,
    "x": 23,
    "y": 54,
    "id": 120001,
    "type": 22,
    "rotation": 3
  },
  {
    "plane": 0,
    "i": 28,
    "j": 25,
    "x": 20,
    "y": 41,
    "id": 120001,
    "type": 22,
    "rotation": 2
  },
  {
    "plane": 0,
    "i": 25,
    "j": 26,
    "x": 8,
    "y": 2,
    "id": 120001,
    "type": 22,
    "rotation": 2
  },
  {
    "plane": 0,
    "i": 25,
    "j": 26,
    "x": 9,
    "y": 4,
    "id": 120001,
    "type": 22,
    "rotation": 1
  },
  {
    "plane": 0,
    "i": 25,
    "j": 26,
    "x": 10,
    "y": 20,
    "id": 120001,
    "type": 22,
    "rotation": 0
  },
  {
    "plane": 0,
    "i": 25,
    "j": 26,
    "x": 11,
    "y": 6,
    "id": 120001,
    "type": 22,
    "rotation": 2
  },
  {
    "plane": 0,
    "i": 25,
    "j": 26,
    "x": 12,
    "y": 19,
    "id": 120001,
    "type": 22,
    "rotation": 1
  },
  {
    "plane": 0,
    "i": 25,
    "j": 26,
    "x": 13,
    "y": 15,
    "id": 120001,
    "type": 22,
    "rotation": 3
  },
  {
    "plane": 0,
    "i": 25,
    "j": 26,
    "x": 14,
    "y": 5,
    "id": 120001,
    "type": 22,
    "rotation": 2
  },
  {
    "plane": 0,
    "i": 25,
    "j": 26,
    "x": 15,
    "y": 21,
    "id": 120001,
    "type": 22,
    "rotation": 3
  },
  {
    "plane": 0,
    "i": 25,
    "j": 26,
    "x": 16,
    "y": 12,
    "id": 120001,
    "type": 22,
    "rotation": 0
  },
  {
    "plane": 0,
    "i": 25,
    "j": 26,
    "x": 16,
    "y": 24,
    "id": 120001,
    "type": 22,
    "rotation": 2
  },
  {
    "plane": 0,
    "i": 25,
    "j": 26,
    "x": 17,
    "y": 4,
    "id": 120001,
    "type": 22,
    "rotation": 3
  },
  {
    "plane": 0,
    "i": 25,
    "j": 26,
    "x": 17,
    "y": 6,
    "id": 120001,
    "type": 22,
    "rotation": 1
  },
  {
    "plane": 0,
    "i": 25,
    "j": 26,
    "x": 17,
    "y": 23,
    "id": 120001,
    "type": 22,
    "rotation": 2
  },
  {
    "plane": 0,
    "i": 25,
    "j": 26,
    "x": 18,
    "y": 7,
    "id": 120001,
    "type": 22,
    "rotation": 0
  },
  {
    "plane": 0,
    "i": 25,
    "j": 26,
    "x": 19,
    "y": 1,
    "id": 120001,
    "type": 22,
    "rotation": 1
  },
  {
    "plane": 0,
    "i": 25,
    "j": 26,
    "x": 19,
    "y": 2,
    "id": 120001,
    "type": 22,
    "rotation": 0
  },
  {
    "plane": 0,
    "i": 25,
    "j": 26,
    "x": 21,
    "y": 23,
    "id": 120001,
    "type": 22,
    "rotation": 2
  },
  {
    "plane": 0,
    "i": 25,
    "j": 26,
    "x": 21,
    "y": 26,
    "id": 120001,
    "type": 22,
    "rotation": 1
  },
  {
    "plane": 0,
    "i": 25,
    "j": 26,
    "x": 22,
    "y": 13,
    "id": 120001,
    "type": 22,
    "rotation": 1
  },
  {
    "plane": 0,
    "i": 25,
    "j": 26,
    "x": 23,
    "y": 0,
    "id": 120001,
    "type": 22,
    "rotation": 0
  },
  {
    "plane": 0,
    "i": 25,
    "j": 26,
    "x": 28,
    "y": 10,
    "id": 120001,
    "type": 22,
    "rotation": 0
  },
  {
    "plane": 0,
    "i": 25,
    "j": 26,
    "x": 29,
    "y": 13,
    "id": 120001,
    "type": 22,
    "rotation": 1
  },
  {
    "plane": 0,
    "i": 25,
    "j": 26,
    "x": 29,
    "y": 15,
    "id": 120001,
    "type": 22,
    "rotation": 3
  },
  {
    "plane": 0,
    "i": 25,
    "j": 26,
    "x": 29,
    "y": 17,
    "id": 120001,
    "type": 22,
    "rotation": 2
  },
  {
    "plane": 0,
    "i": 25,
    "j": 26,
    "x": 29,
    "y": 18,
    "id": 120001,
    "type": 22,
    "rotation": 1
  },
  {
    "plane": 0,
    "i": 25,
    "j": 26,
    "x": 30,
    "y": 0,
    "id": 120001,
    "type": 22,
    "rotation": 2
  },
  {
    "plane": 0,
    "i": 25,
    "j": 26,
    "x": 30,
    "y": 17,
    "id": 120001,
    "type": 22,
    "rotation": 1
  },
  {
    "plane": 0,
    "i": 25,
    "j": 26,
    "x": 30,
    "y": 21,
    "id": 120001,
    "type": 22,
    "rotation": 0
  },
  {
    "plane": 0,
    "i": 25,
    "j": 26,
    "x": 32,
    "y": 6,
    "id": 120001,
    "type": 22,
    "rotation": 1
  },
  {
    "plane": 0,
    "i": 25,
    "j": 26,
    "x": 32,
    "y": 23,
    "id": 120001,
    "type": 22,
    "rotation": 2
  },
  {
    "plane": 0,
    "i": 25,
    "j": 26,
    "x": 33,
    "y": 3,
    "id": 120001,
    "type": 22,
    "rotation": 3
  },
  {
    "plane": 0,
    "i": 25,
    "j": 26,
    "x": 34,
    "y": 1,
    "id": 120001,
    "type": 22,
    "rotation": 2
  },
  {
    "plane": 0,
    "i": 25,
    "j": 26,
    "x": 34,
    "y": 4,
    "id": 120001,
    "type": 22,
    "rotation": 2
  },
  {
    "plane": 0,
    "i": 25,
    "j": 26,
    "x": 34,
    "y": 11,
    "id": 120001,
    "type": 22,
    "rotation": 0
  },
  {
    "plane": 0,
    "i": 25,
    "j": 26,
    "x": 34,
    "y": 23,
    "id": 120001,
    "type": 22,
    "rotation": 1
  },
  {
    "plane": 0,
    "i": 25,
    "j": 26,
    "x": 35,
    "y": 0,
    "id": 120001,
    "type": 22,
    "rotation": 1
  },
  {
    "plane": 0,
    "i": 25,
    "j": 26,
    "x": 35,
    "y": 12,
    "id": 120001,
    "type": 22,
    "rotation": 2
  },
  {
    "plane": 0,
    "i": 25,
    "j": 26,
    "x": 35,
    "y": 25,
    "id": 120001,
    "type": 22,
    "rotation": 3
  },
  {
    "plane": 0,
    "i": 25,
    "j": 26,
    "x": 36,
    "y": 23,
    "id": 120001,
    "type": 22,
    "rotation": 0
  },
  {
    "plane": 0,
    "i": 25,
    "j": 26,
    "x": 36,
    "y": 24,
    "id": 120001,
    "type": 22,
    "rotation": 2
  },
  {
    "plane": 0,
    "i": 25,
    "j": 26,
    "x": 38,
    "y": 17,
    "id": 120001,
    "type": 22,
    "rotation": 2
  },
  {
    "plane": 0,
    "i": 25,
    "j": 26,
    "x": 39,
    "y": 1,
    "id": 120001,
    "type": 22,
    "rotation": 2
  },
  {
    "plane": 0,
    "i": 25,
    "j": 26,
    "x": 40,
    "y": 12,
    "id": 120001,
    "type": 22,
    "rotation": 3
  },
  {
    "plane": 0,
    "i": 25,
    "j": 26,
    "x": 43,
    "y": 19,
    "id": 120001,
    "type": 22,
    "rotation": 3
  },
  {
    "plane": 0,
    "i": 25,
    "j": 26,
    "x": 44,
    "y": 19,
    "id": 120001,
    "type": 22,
    "rotation": 2
  },
  {
    "plane": 0,
    "i": 25,
    "j": 26,
    "x": 44,
    "y": 20,
    "id": 120001,
    "type": 22,
    "rotation": 0
  },
  {
    "plane": 0,
    "i": 25,
    "j": 26,
    "x": 46,
    "y": 15,
    "id": 120001,
    "type": 22,
    "rotation": 1
  },
  {
    "plane": 0,
    "i": 25,
    "j": 26,
    "x": 54,
    "y": 5,
    "id": 120001,
    "type": 22,
    "rotation": 3
  },
  {
    "plane": 0,
    "i": 25,
    "j": 26,
    "x": 55,
    "y": 2,
    "id": 120001,
    "type": 22,
    "rotation": 0
  },
  {
    "plane": 0,
    "i": 25,
    "j": 26,
    "x": 56,
    "y": 3,
    "id": 120001,
    "type": 22,
    "rotation": 1
  },
  {
    "plane": 0,
    "i": 25,
    "j": 26,
    "x": 60,
    "y": 3,
    "id": 120001,
    "type": 22,
    "rotation": 3
  },
  {
    "plane": 0,
    "i": 25,
    "j": 26,
    "x": 61,
    "y": 2,
    "id": 120001,
    "type": 22,
    "rotation": 2
  },
  {
    "plane": 1,
    "i": 25,
    "j": 26,
    "x": 28,
    "y": 21,
    "id": 120001,
    "type": 22,
    "rotation": 0
  },
  {
    "plane": 1,
    "i": 25,
    "j": 26,
    "x": 29,
    "y": 20,
    "id": 120001,
    "type": 22,
    "rotation": 0
  },
  {
    "plane": 1,
    "i": 25,
    "j": 26,
    "x": 29,
    "y": 24,
    "id": 120001,
    "type": 22,
    "rotation": 3
  },
  {
    "plane": 1,
    "i": 25,
    "j": 26,
    "x": 31,
    "y": 22,
    "id": 120001,
    "type": 22,
    "rotation": 2
  },
  {
    "plane": 1,
    "i": 25,
    "j": 26,
    "x": 31,
    "y": 25,
    "id": 120001,
    "type": 22,
    "rotation": 2
  },
  {
    "plane": 0,
    "i": 26,
    "j": 26,
    "x": 6,
    "y": 1,
    "id": 120001,
    "type": 22,
    "rotation": 2
  },
  {
    "plane": 0,
    "i": 26,
    "j": 26,
    "x": 6,
    "y": 12,
    "id": 120001,
    "type": 22,
    "rotation": 3
  },
  {
    "plane": 0,
    "i": 26,
    "j": 26,
    "x": 6,
    "y": 14,
    "id": 120001,
    "type": 22,
    "rotation": 3
  },
  {
    "plane": 0,
    "i": 26,
    "j": 26,
    "x": 7,
    "y": 10,
    "id": 120001,
    "type": 22,
    "rotation": 2
  },
  {
    "plane": 0,
    "i": 26,
    "j": 26,
    "x": 8,
    "y": 2,
    "id": 120001,
    "type": 22,
    "rotation": 1
  },
  {
    "plane": 0,
    "i": 26,
    "j": 26,
    "x": 8,
    "y": 8,
    "id": 120001,
    "type": 22,
    "rotation": 2
  },
  {
    "plane": 0,
    "i": 26,
    "j": 26,
    "x": 11,
    "y": 2,
    "id": 120001,
    "type": 22,
    "rotation": 0
  },
  {
    "plane": 0,
    "i": 26,
    "j": 26,
    "x": 12,
    "y": 4,
    "id": 120001,
    "type": 22,
    "rotation": 0
  },
  {
    "plane": 0,
    "i": 26,
    "j": 26,
    "x": 17,
    "y": 6,
    "id": 120001,
    "type": 22,
    "rotation": 1
  },
  {
    "plane": 0,
    "i": 26,
    "j": 26,
    "x": 18,
    "y": 18,
    "id": 120001,
    "type": 22,
    "rotation": 2
  },
  {
    "plane": 0,
    "i": 26,
    "j": 26,
    "x": 18,
    "y": 26,
    "id": 120001,
    "type": 22,
    "rotation": 1
  },
  {
    "plane": 0,
    "i": 26,
    "j": 26,
    "x": 19,
    "y": 18,
    "id": 120001,
    "type": 22,
    "rotation": 2
  },
  {
    "plane": 0,
    "i": 26,
    "j": 26,
    "x": 20,
    "y": 18,
    "id": 120001,
    "type": 22,
    "rotation": 3
  },
  {
    "plane": 0,
    "i": 26,
    "j": 26,
    "x": 43,
    "y": 10,
    "id": 120001,
    "type": 22,
    "rotation": 2
  },
  {
    "plane": 0,
    "i": 26,
    "j": 26,
    "x": 45,
    "y": 7,
    "id": 120001,
    "type": 22,
    "rotation": 0
  },
  {
    "plane": 0,
    "i": 26,
    "j": 26,
    "x": 45,
    "y": 8,
    "id": 120001,
    "type": 22,
    "rotation": 1
  },
  {
    "plane": 0,
    "i": 26,
    "j": 26,
    "x": 47,
    "y": 4,
    "id": 120001,
    "type": 22,
    "rotation": 2
  },
  {
    "plane": 0,
    "i": 26,
    "j": 26,
    "x": 48,
    "y": 6,
    "id": 120001,
    "type": 22,
    "rotation": 1
  },
  {
    "plane": 0,
    "i": 26,
    "j": 26,
    "x": 48,
    "y": 20,
    "id": 120001,
    "type": 22,
    "rotation": 2
  },
  {
    "plane": 0,
    "i": 26,
    "j": 26,
    "x": 49,
    "y": 21,
    "id": 120001,
    "type": 22,
    "rotation": 2
  },
  {
    "plane": 0,
    "i": 26,
    "j": 26,
    "x": 50,
    "y": 3,
    "id": 120001,
    "type": 22,
    "rotation": 0
  },
  {
    "plane": 0,
    "i": 26,
    "j": 26,
    "x": 50,
    "y": 13,
    "id": 120001,
    "type": 22,
    "rotation": 2
  },
  {
    "plane": 0,
    "i": 26,
    "j": 26,
    "x": 50,
    "y": 18,
    "id": 120001,
    "type": 22,
    "rotation": 0
  },
  {
    "plane": 0,
    "i": 26,
    "j": 26,
    "x": 50,
    "y": 21,
    "id": 120001,
    "type": 22,
    "rotation": 1
  },
  {
    "plane": 0,
    "i": 26,
    "j": 26,
    "x": 51,
    "y": 14,
    "id": 120001,
    "type": 22,
    "rotation": 1
  },
  {
    "plane": 0,
    "i": 26,
    "j": 26,
    "x": 56,
    "y": 13,
    "id": 120001,
    "type": 22,
    "rotation": 0
  },
  {
    "plane": 1,
    "i": 26,
    "j": 26,
    "x": 12,
    "y": 0,
    "id": 120001,
    "type": 22,
    "rotation": 3
  },
  {
    "plane": 1,
    "i": 26,
    "j": 26,
    "x": 12,
    "y": 2,
    "id": 120001,
    "type": 22,
    "rotation": 1
  },
  {
    "plane": 0,
    "i": 26,
    "j": 26,
    "x": 26,
    "y": 13,
    "id": 120001,
    "type": 22,
    "rotation": 1
  },
  {
    "plane": 0,
    "i": 26,
    "j": 26,
    "x": 27,
    "y": 14,
    "id": 120001,
    "type": 22,
    "rotation": 2
  },
  {
    "plane": 0,
    "i": 26,
    "j": 26,
    "x": 32,
    "y": 14,
    "id": 120001,
    "type": 22,
    "rotation": 2
  },
  {
    "plane": 1,
    "i": 16,
    "j": 27,
    "x": 1,
    "y": 53,
    "id": 120001,
    "type": 22,
    "rotation": 0
  },
  {
    "plane": 1,
    "i": 16,
    "j": 27,
    "x": 5,
    "y": 38,
    "id": 120001,
    "type": 22,
    "rotation": 0
  },
  {
    "plane": 1,
    "i": 16,
    "j": 27,
    "x": 5,
    "y": 59,
    "id": 120001,
    "type": 22,
    "rotation": 0
  },
  {
    "plane": 1,
    "i": 16,
    "j": 27,
    "x": 10,
    "y": 28,
    "id": 120001,
    "type": 22,
    "rotation": 1
  },
  {
    "plane": 1,
    "i": 16,
    "j": 27,
    "x": 11,
    "y": 53,
    "id": 120001,
    "type": 22,
    "rotation": 2
  },
  {
    "plane": 1,
    "i": 16,
    "j": 27,
    "x": 12,
    "y": 39,
    "id": 120001,
    "type": 22,
    "rotation": 1
  },
  {
    "plane": 1,
    "i": 16,
    "j": 27,
    "x": 24,
    "y": 37,
    "id": 120001,
    "type": 22,
    "rotation": 1
  },
  {
    "plane": 1,
    "i": 16,
    "j": 27,
    "x": 29,
    "y": 47,
    "id": 120001,
    "type": 22,
    "rotation": 0
  },
  {
    "plane": 2,
    "i": 16,
    "j": 27,
    "x": 5,
    "y": 49,
    "id": 120001,
    "type": 22,
    "rotation": 2
  },
  {
    "plane": 2,
    "i": 16,
    "j": 27,
    "x": 20,
    "y": 43,
    "id": 120001,
    "type": 22,
    "rotation": 2
  },
  {
    "plane": 0,
    "i": 26,
    "j": 29,
    "x": 26,
    "y": 33,
    "id": 120001,
    "type": 22,
    "rotation": 3
  },
  {
    "plane": 0,
    "i": 26,
    "j": 29,
    "x": 39,
    "y": 13,
    "id": 120001,
    "type": 22,
    "rotation": 1
  },
  {
    "plane": 0,
    "i": 26,
    "j": 29,
    "x": 48,
    "y": 6,
    "id": 120001,
    "type": 22,
    "rotation": 0
  },
  {
    "plane": 0,
    "i": 26,
    "j": 29,
    "x": 49,
    "y": 0,
    "id": 120001,
    "type": 22,
    "rotation": 0
  },
  {
    "plane": 0,
    "i": 28,
    "j": 29,
    "x": 14,
    "y": 38,
    "id": 120001,
    "type": 22,
    "rotation": 0
  },
  {
    "plane": 0,
    "i": 28,
    "j": 29,
    "x": 21,
    "y": 26,
    "id": 120001,
    "type": 22,
    "rotation": 0
  },
  {
    "plane": 0,
    "i": 28,
    "j": 29,
    "x": 36,
    "y": 33,
    "id": 120001,
    "type": 22,
    "rotation": 0
  },
  {
    "plane": 0,
    "i": 28,
    "j": 29,
    "x": 36,
    "y": 37,
    "id": 120001,
    "type": 22,
    "rotation": 0
  },
  {
    "plane": 0,
    "i": 29,
    "j": 29,
    "x": 8,
    "y": 33,
    "id": 120001,
    "type": 22,
    "rotation": 0
  },
  {
    "plane": 0,
    "i": 29,
    "j": 29,
    "x": 39,
    "y": 30,
    "id": 120001,
    "type": 22,
    "rotation": 0
  },
  {
    "plane": 0,
    "i": 29,
    "j": 29,
    "x": 53,
    "y": 17,
    "id": 120001,
    "type": 22,
    "rotation": 3
  },
  {
    "plane": 0,
    "i": 29,
    "j": 29,
    "x": 57,
    "y": 16,
    "id": 120001,
    "type": 22,
    "rotation": 0
  },
  {
    "plane": 0,
    "i": 29,
    "j": 29,
    "x": 61,
    "y": 38,
    "id": 120001,
    "type": 22,
    "rotation": 0
  },
  {
    "plane": 0,
    "i": 27,
    "j": 30,
    "x": 8,
    "y": 60,
    "id": 120001,
    "type": 22,
    "rotation": 0
  },
  {
    "plane": 0,
    "i": 27,
    "j": 30,
    "x": 25,
    "y": 49,
    "id": 120001,
    "type": 22,
    "rotation": 3
  },
  {
    "plane": 0,
    "i": 27,
    "j": 30,
    "x": 25,
    "y": 60,
    "id": 120001,
    "type": 22,
    "rotation": 0
  },
  {
    "plane": 0,
    "i": 27,
    "j": 30,
    "x": 33,
    "y": 57,
    "id": 120001,
    "type": 22,
    "rotation": 1
  },
  {
    "plane": 0,
    "i": 27,
    "j": 30,
    "x": 34,
    "y": 44,
    "id": 120001,
    "type": 22,
    "rotation": 3
  },
  {
    "plane": 0,
    "i": 18,
    "j": 31,
    "x": 14,
    "y": 41,
    "id": 120001,
    "type": 22,
    "rotation": 1
  },
  {
    "plane": 0,
    "i": 18,
    "j": 31,
    "x": 14,
    "y": 42,
    "id": 120001,
    "type": 22,
    "rotation": 1
  },
  {
    "plane": 0,
    "i": 18,
    "j": 31,
    "x": 21,
    "y": 24,
    "id": 120001,
    "type": 22,
    "rotation": 0
  },
  {
    "plane": 0,
    "i": 18,
    "j": 31,
    "x": 30,
    "y": 18,
    "id": 120001,
    "type": 22,
    "rotation": 2
  },
  {
    "plane": 0,
    "i": 18,
    "j": 31,
    "x": 30,
    "y": 20,
    "id": 120001,
    "type": 22,
    "rotation": 2
  },
  {
    "plane": 0,
    "i": 18,
    "j": 31,
    "x": 30,
    "y": 23,
    "id": 120001,
    "type": 22,
    "rotation": 3
  },
  {
    "plane": 0,
    "i": 18,
    "j": 31,
    "x": 31,
    "y": 25,
    "id": 120001,
    "type": 22,
    "rotation": 0
  },
  {
    "plane": 0,
    "i": 18,
    "j": 31,
    "x": 31,
    "y": 26,
    "id": 120001,
    "type": 22,
    "rotation": 2
  },
  {
    "plane": 0,
    "i": 18,
    "j": 31,
    "x": 32,
    "y": 40,
    "id": 120001,
    "type": 22,
    "rotation": 0
  },
  {
    "plane": 0,
    "i": 18,
    "j": 31,
    "x": 32,
    "y": 53,
    "id": 120001,
    "type": 22,
    "rotation": 3
  },
  {
    "plane": 0,
    "i": 18,
    "j": 31,
    "x": 33,
    "y": 41,
    "id": 120001,
    "type": 22,
    "rotation": 2
  },
  {
    "plane": 0,
    "i": 18,
    "j": 31,
    "x": 33,
    "y": 46,
    "id": 120001,
    "type": 22,
    "rotation": 3
  },
  {
    "plane": 0,
    "i": 18,
    "j": 31,
    "x": 33,
    "y": 52,
    "id": 120001,
    "type": 22,
    "rotation": 2
  },
  {
    "plane": 0,
    "i": 18,
    "j": 31,
    "x": 36,
    "y": 31,
    "id": 120001,
    "type": 22,
    "rotation": 0
  },
  {
    "plane": 0,
    "i": 18,
    "j": 31,
    "x": 37,
    "y": 51,
    "id": 120001,
    "type": 22,
    "rotation": 1
  },
  {
    "plane": 0,
    "i": 18,
    "j": 31,
    "x": 38,
    "y": 51,
    "id": 120001,
    "type": 22,
    "rotation": 2
  },
  {
    "plane": 0,
    "i": 18,
    "j": 31,
    "x": 42,
    "y": 21,
    "id": 120001,
    "type": 22,
    "rotation": 2
  },
  {
    "plane": 0,
    "i": 18,
    "j": 31,
    "x": 43,
    "y": 36,
    "id": 120001,
    "type": 22,
    "rotation": 1
  },
  {
    "plane": 0,
    "i": 18,
    "j": 31,
    "x": 44,
    "y": 29,
    "id": 120001,
    "type": 22,
    "rotation": 0
  },
  {
    "plane": 0,
    "i": 18,
    "j": 31,
    "x": 44,
    "y": 34,
    "id": 120001,
    "type": 22,
    "rotation": 3
  },
  {
    "plane": 0,
    "i": 18,
    "j": 31,
    "x": 47,
    "y": 29,
    "id": 120001,
    "type": 22,
    "rotation": 3
  },
  {
    "plane": 0,
    "i": 42,
    "j": 57,
    "x": 36,
    "y": 59,
    "id": 120001,
    "type": 22,
    "rotation": 2
  },
  {
    "plane": 0,
    "i": 18,
    "j": 64,
    "x": 52,
    "y": 43,
    "id": 120001,
    "type": 22,
    "rotation": 2
  },
  {
    "plane": 0,
    "i": 54,
    "j": 118,
    "x": 10,
    "y": 33,
    "id": 120001,
    "type": 22,
    "rotation": 1
  },
  {
    "plane": 0,
    "i": 54,
    "j": 118,
    "x": 12,
    "y": 46,
    "id": 120001,
    "type": 22,
    "rotation": 0
  },
  {
    "plane": 0,
    "i": 54,
    "j": 118,
    "x": 14,
    "y": 35,
    "id": 120001,
    "type": 22,
    "rotation": 1
  }
]