[
  {
    "plane": 0,
    "i": 28,
    "j": 19,
    "x": 44,
    "y": 34,
    "id": 121564,
    "type": 10,
    "rotation": 0
  },
  {
    "plane": 0,
    "i": 28,
    "j": 19,
    "x": 58,
    "y": 27,
    "id": 121564,
    "type": 11,
    "rotation": 0
  },
  {
    "plane": 0,
    "i": 29,
    "j": 19,
    "x": 60,
    "y": 28,
    "id": 121564,
    "type": 11,
    "rotation": 0
  },
  {
    "plane": 0,
    "i": 30,
    "j": 19,
    "x": 6,
    "y": 10,
    "id": 121564,
    "type": 11,
    "rotation": 2
  },
  {
    "plane": 0,
    "i": 26,
    "j": 25,
    "x": 25,
    "y": 29,
    "id": 121564,
    "type": 11,
    "rotation": 1
  },
  {
    "plane": 0,
    "i": 28,
    "j": 29,
    "x": 44,
    "y": 34,
    "id": 121564,
    "type": 10,
    "rotation": 0
  },
  {
    "plane": 0,
    "i": 28,
    "j": 29,
    "x": 58,
    "y": 27,
    "id": 121564,
    "type": 11,
    "rotation": 0
  },
  {
    "plane": 0,
    "i": 29,
    "j": 29,
    "x": 60,
    "y": 28,
    "id": 121564,
    "type": 11,
    "rotation": 0
  },
  {
    "plane": 0,
    "i": 30,
    "j": 29,
    "x": 6,
    "y": 10,
    "id": 121564,
    "type": 11,
    "rotation": 2
  }
]