[
  {
    "plane": 0,
    "i": 47,
    "j": 56,
    "x": 10,
    "y": 39,
    "id": 124472,
    "type": 10,
    "rotation": 0
  },
  {
    "plane": 0,
    "i": 47,
    "j": 56,
    "x": 10,
    "y": 44,
    "id": 124472,
    "type": 10,
    "rotation": 0
  },
  {
    "plane": 0,
    "i": 47,
    "j": 56,
    "x": 10,
    "y": 53,
    "id": 124472,
    "type": 10,
    "rotation": 0
  },
  {
    "plane": 0,
    "i": 47,
    "j": 56,
    "x": 14,
    "y": 59,
    "id": 124472,
    "type": 10,
    "rotation": 1
  },
  {
    "plane": 0,
    "i": 47,
    "j": 56,
    "x": 18,
    "y": 36,
    "id": 124472,
    "type": 10,
    "rotation": 3
  },
  {
    "plane": 0,
    "i": 47,
    "j": 56,
    "x": 19,
    "y": 58,
    "id": 124472,
    "type": 10,
    "rotation": 1
  },
  {
    "plane": 0,
    "i": 47,
    "j": 56,
    "x": 30,
    "y": 36,
    "id": 124472,
    "type": 10,
    "rotation": 3
  },
  {
    "plane": 0,
    "i": 47,
    "j": 56,
    "x": 32,
    "y": 41,
    "id": 124472,
    "type": 10,
    "rotation": 2
  },
  {
    "plane": 0,
    "i": 47,
    "j": 56,
    "x": 32,
    "y": 54,
    "id": 124472,
    "type": 10,
    "rotation": 2
  }
]