[
  {
    "plane": 0,
    "i": 54,
    "j": 51,
    "x": 28,
    "y": 27,
    "id": 34305,
    "type": 1,
    "rotation": 3
  },
  {
    "plane": 0,
    "i": 54,
    "j": 51,
    "x": 29,
    "y": 26,
    "id": 34305,
    "type": 1,
    "rotation": 3
  },
  {
    "plane": 0,
    "i": 41,
    "j": 78,
    "x": 28,
    "y": 27,
    "id": 34305,
    "type": 1,
    "rotation": 3
  },
  {
    "plane": 0,
    "i": 41,
    "j": 78,
    "x": 29,
    "y": 26,
    "id": 34305,
    "type": 1,
    "rotation": 3
  }
]