[
  {
    "plane": 0,
    "i": 16,
    "j": 97,
    "x": 37,
    "y": 39,
    "id": 71390,
    "type": 9,
    "rotation": 2
  },
  {
    "plane": 0,
    "i": 16,
    "j": 97,
    "x": 38,
    "y": 39,
    "id": 71390,
    "type": 9,
    "rotation": 3
  },
  {
    "plane": 0,
    "i": 20,
    "j": 97,
    "x": 32,
    "y": 38,
    "id": 71390,
    "type": 1,
    "rotation": 3
  },
  {
    "plane": 0,
    "i": 20,
    "j": 97,
    "x": 35,
    "y": 26,
    "id": 71390,
    "type": 1,
    "rotation": 0
  },
  {
    "plane": 0,
    "i": 20,
    "j": 97,
    "x": 43,
    "y": 35,
    "id": 71390,
    "type": 1,
    "rotation": 0
  },
  {
    "plane": 0,
    "i": 17,
    "j": 101,
    "x": 1,
    "y": 30,
    "id": 71390,
    "type": 1,
    "rotation": 1
  },
  {
    "plane": 0,
    "i": 17,
    "j": 101,
    "x": 10,
    "y": 15,
    "id": 71390,
    "type": 0,
    "rotation": 2
  },
  {
    "plane": 0,
    "i": 17,
    "j": 101,
    "x": 14,
    "y": 31,
    "id": 71390,
    "type": 1,
    "rotation": 2
  },
  {
    "plane": 0,
    "i": 17,
    "j": 101,
    "x": 41,
    "y": 38,
    "id": 71390,
    "type": 1,
    "rotation": 1
  },
  {
    "plane": 0,
    "i": 17,
    "j": 101,
    "x": 41,
    "y": 40,
    "id": 71390,
    "type": 1,
    "rotation": 2
  },
  {
    "plane": 0,
    "i": 17,
    "j": 101,
    "x": 42,
    "y": 40,
    "id": 71390,
    "type": 9,
    "rotation": 2
  },
  {
    "plane": 0,
    "i": 18,
    "j": 101,
    "x": 43,
    "y": 20,
    "id": 71390,
    "type": 1,
    "rotation": 1
  },
  {
    "plane": 0,
    "i": 18,
    "j": 101,
    "x": 43,
    "y": 21,
    "id": 71390,
    "type": 9,
    "rotation": 1
  },
  {
    "plane": 0,
    "i": 18,
    "j": 101,
    "x": 51,
    "y": 39,
    "id": 71390,
    "type": 0,
    "rotation": 1
  },
  {
    "plane": 0,
    "i": 18,
    "j": 101,
    "x": 54,
    "y": 46,
    "id": 71390,
    "type": 1,
    "rotation": 3
  }
]